Workbook

Sheet NOMINA DE NOVIEMBRE
A1: NÓMINA DE PERSONAL DE NOVIEMBRE 2025
A4: Asociado - Número de Documento | B4: Asociado - Estado | C4: Asociado - Nombre Completo | D4: Asociado - Código de Ficha | E4: Asociado - Sexo | F4: Trabajo - Fecha Ingreso Compañía | G4: Asociado - Fecha de Nacimiento | H4: Asociado - Teléfono Particular | I4: Trabajo - Nombre Área | J4: Trabajo - Nombre Sub-área Asignada(o) | K4: Trabajo - Cargo | L4: Trabajo - Tipo de Contrato | M4: Trabajo - Tipo de Jornada | N4: Trabajo - Sindicato | O4: Trabajo - Jornada Laboral | P4: Trabajo - Horas Semanales | Q4: Trabajo - Fecha Vencimiento Contrato
A5: 16.369.570-7 | B5: Activo | C5: Fuentes Castillo Macarena Alejandra | D5: F1 | E5: F | F5: 45873 | G5: 32003 | H5: 994060922 | I5: F&B | J5: OFICINA DE BANQUETES | K5: COORDINADOR(A) DE BANQUETES | L5: Indefinido | M5: Ordinaria ART 22 | N5: Extensión de Beneficio Sindicato 1 | O5: mensual | P5: 42.5
A6: 23.816.541-5 | B6: Activo | C6: Pecovnik Cortes Igor | D6: F1 | E6: M | F6: 42911 | G6: 26528 | H6: 999368991 | I6: ROOMS | J6: GROOMS | K6: Grooms/Portero/Valet | L6: Indefinido | M6: Ordinaria ART 22 | N6: Sindicato 1 | O6: mensual | P6: 42.5
A7: 19.894.223-5 | B7: Activo | C7: Faundez Vallejos Ailin Cricel | D7: F1 | E7: F | F7: 45740 | G7: 35733 | H7: 966647464 | I7: ADMINISTRACION Y GERENCIA | J7: SEGURIDAD | K7: GUARDIA | L7: Indefinido | M7: Ordinaria ART 22 | N7: Sindicato 1 | O7: mensual | P7: 44
A8: 19.429.624-k | B8: Activo | C8: Pons Valenzuela Fernanda Edith | D8: F1 | E8: F | F8: 45733 | G8: 35314 | H8: 957168583 | I8: F&B | J8: COCINA | K8: COMMIS | L8: Indefinido | M8: Ordinaria ART 22 | N8: Sindicato 1 | O8: mensual | P8: 42.5
A9: 25.399.125-9 | B9: Activo | C9: Seljak Piña Franz Isidro | D9: F1 | E9: F | F9: 45698 | G9: 34083 | H9: 958147239 | I9: F&B | J9: COCINA | K9: CHEF DE PARTIE | L9: Indefinido | M9: Ordinaria ART 22 | N9: Sindicato 1 | O9: mensual | P9: 42.5
A10: 19.837.527-6 | B10: Activo | C10: Troncoso Enriquez Luis David | D10: F1 | E10: M | F10: 45873 | G10: 35732 | H10: 965198972 | I10: ROOMS | J10: GUEST SERVICES AGENT | K10: GUEST SERVICE AGENT | L10: Indefinido | M10: Ordinaria ART 22 | N10: Extensión de Beneficio Sindicato 2 | O10: mensual | P10: 42.5
A11: 10.234.877-k | B11: Activo | C11: Salas Villaceca David Antonio | D11: F1 | E11: M | F11: 38153 | G11: 23601 | H11: 988189560 | I11: ADMINISTRACION Y GERENCIA | J11: CONTRALORIA | K11: CAJERO CENTRAL/COBRADOR | L11: Indefinido | M11: Exenta ART 22 | N11: Extensión de Beneficio Sindicato 1 | O11: mensual | P11: 42.5
A12: 26.610.495-2 | B12: Inactivo | C12: Pierre - Esaie | D12: F-1jul25 | E12: M | F12: 45842 | G12: 34217 | H12: 968759462 | I12: F&B | J12: STEWARD | K12: PLAQUECERO | L12: Plazo fijo | M12: Ordinaria ART 22 | N12: Extensión de Beneficio Sindicato 1 | O12: mensual | P12: 42.5
A13: 17.924.524-8 | B13: Activo | C13: Marinao Cid Gabriel Isaías | D13: F1 | E13: M | F13: 45810 | G13: 33394 | H13: 926220231 | I13: ADMINISTRACION Y GERENCIA | J13: SEGURIDAD | K13: GUARDIA | L13: Indefinido | M13: Ordinaria ART 22 | N13: Sindicato 1 | O13: mensual | P13: 44
A14: 21.286.136-7 | B14: Activo | C14: Fieldhouse Reyes Alonso Emilio | D14: F1 | E14: M | F14: 45864 | G14: 37736 | H14: 965773140 | I14: ROOMS | J14: GUEST SERVICES AGENT | K14: GUEST SERVICE AGENT | L14: Indefinido | M14: Ordinaria ART 22 | N14: Sindicato 1 | O14: mensual | P14: 42.5
A15: 15.381.940-8 | B15: Activo | C15: Mora Gutierrez Rodrigo Alejandro | D15: F1 | E15: M | F15: 45854 | G15: 30236 | H15: 973379381 | I15: F&B | J15: STEWARD | K15: PLAQUECERO | L15: Indefinido | M15: Ordinaria ART 22 | N15: Sindicato 1 | O15: mensual | P15: 42.5
A16: 9.608.528-1 | B16: Activo | C16: Sepulveda Veloso Javier Antonio | D16: F1 | E16: M | F16: 45356 | G16: 23263 | H16: 997339466 | I16: ADMINISTRACION Y GERENCIA | J16: SEGURIDAD | K16: GUARDIA | L16: Indefinido | M16: Ordinaria ART 22 | N16: Sindicato 1 | O16: mensual | P16: 44
... A204: 21.495.104-5 | B204: Activo | C204: Javia Pinto Ignacio Antonio | D204: F-3oct25 | E204: M | F204: 45949 | G204: 38007 | H204: 932115423 | I204: F&B | J204: EL BOHIO | K204: GARZON/CAJERO OUTLETS | L204: Plazo fijo | M204: Ordinaria ART 22 | N204: Extensión de Beneficio Sindicato 2 | O204: mensual | P204: 42.5
A205: 20.960.571-6 | B205: Inactivo | C205: Mora Gonzalez Williams Alberto | D205: F-3oct25 | E205: M | F205: 45949 | G205: 37282 | H205: 990813163 | I205: F&B | J205: EL BOHIO | K205: GARZON/CAJERO OUTLETS | L205: Plazo fijo | M205: Ordinaria ART 22 | O205: mensual | P205: 42.5
A206: 20.049.364-8 | B206: Activo | C206: Cortés Romero Ignacio Javier | D206: F1 | E206: M | F206: 45873 | G206: 36260 | H206: 986115473 | I206: INGENIERIA | J206: INGENIERIA | K206: KEN FIX IT | L206: Indefinido | M206: Ordinaria ART 22 | N206: Extensión de Beneficio Sindicato 2 | O206: mensual | P206: 42.5
A207: 19.634.304-0 | B207: Activo | C207: Saavedra Rivas Víctor Ariel | D207: F1 | E207: M | F207: 45873 | G207: 35570 | H207: 933460928 | I207: INGENIERIA | J207: INGENIERIA | K207: KEN FIX IT | L207: Indefinido | M207: Ordinaria ART 22 | N207: Extensión de Beneficio Sindicato 2 | O207: mensual | P207: 42.5
A208: 17.317.967-7 | B208: Activo | C208: Maldonado Castro Pablo Andrés | D208: F1 | E208: M | F208: 45873 | G208: 33033 | H208: 932683071 | I208: INGENIERIA | J208: INGENIERIA | K208: ENGINEER II | L208: Indefinido | M208: Ordinaria ART 22 | N208: Sindicato 1 | O208: mensual | P208: 42.5
A209: 22.157.857-0 | B209: Activo | C209: Sanchez Diaz Javier Ignacio | D209: F-4sep25 | E209: M | F209: 45925 | G209: 38904 | H209: 920141902 | I209: F&B | J209: COCINA | K209: COMMIS | L209: Plazo fijo | M209: Ordinaria ART 22 | N209: Extensión de Beneficio Sindicato 1 | O209: mensual | P209: 42.5
A210: 19.892.710-4 | B210: Activo | C210: Acevedo Almonte Bernardita Sofía | D210: F1 | E210: F | F210: 45705 | G210: 35978 | H210: 990802454 | I210: VENTAS Y MARKETING | J210: RELACIONES PUBLICAS | K210: COORDINADORA DE MARKETING | L210: Indefinido | M210: Exenta ART 22 | N210: Sindicato 2 | O210: mensual | P210: 44
A211: 10.637.832-0 | B211: Activo | C211: Novoa Reyes Alejandra Elizabeth | D211: F1 | E211: F | F211: 41071 | G211: 27881 | H211: 984395990 | I211: VENTAS Y MARKETING | J211: VENTAS | K211: ACCOUNT MANAGER | L211: Indefinido | M211: Exenta ART 22 | N211: Sindicato 2 | O211: mensual | P211: 42.5
A212: 21.323.547-8 | B212: Inactivo | C212: Molina Pizarro Genesis Alejandra | D212: F-2oct25 | E212: F | F212: 45938 | G212: 37780 | H212: 976538500 | I212: F&B | J212: ROOM SERVICE | K212: GARZON/CAJERO OUTLETS | L212: Plazo fijo | M212: Ordinaria ART 22 | N212: Extensión de Beneficio Sindicato 1 | O212: mensual | P212: 42.5
A213: 20.590.424-7 | B213: Inactivo | C213: Olivares Contreras Ruben Eliseo | D213: F-2oct25 | E213: M | F213: 45938 | G213: 36788 | H213: 971245851 | I213: F&B | J213: CID | K213: GARZON/CAJERO OUTLETS | L213: Plazo fijo | M213: Ordinaria ART 22 | N213: Extensión de Beneficio Sindicato 1 | O213: mensual | P213: 42.5
A214: 20.054.413-7 | B214: Activo | C214: Lecaros Tapia Francisco Javier | D214: F-1oct25 | E214: M | F214: 45937 | G214: 36179 | H214: 964463846 | I214: F&B | J214: LOBBY BAR | K214: BARTENDER | L214: Plazo fijo | M214: Ordinaria ART 22 | N214: Extensión de Beneficio Sindicato 1 | O214: mensual | P214: 42.5
A215: 20.153.031-8 | B215: Activo | C215: Gonzalez Marileo Francisco Andres | D215: F-2oct25 | E215: M | F215: 45937 | G215: 36607 | H215: 989470565 | I215: F&B | J215: LOBBY BAR | K215: BARTENDER | L215: Plazo fijo | M215: Ordinaria ART 22 | N215: Extensión de Beneficio Sindicato 1 | O215: mensual | P215: 42.5
A216: 13.696.002-4 | B216: Activo | C216: Quintana Contreras Carolina Alejandra | D216: F1 | E216: F | F216: 43640 | G216: 29116 | H216: 964821590 | I216: VENTAS Y MARKETING | J216: VENTAS | K216: ACCOUNT MANAGER | L216: Indefinido | M216: Exenta ART 22 | N216: Sindicato 2 | O216: mensual | P216: 42.5
A217: 25.724.970-0 | B217: Activo | C217: Araujo Moya Naibel Del Valle | D217: F1 | E217: F | F217: 45936 | G217: 31847 | H217: 971772773 | I217: MEMO | J217: PALAFITO | K217: CHEF ENCARGADO DE PALAFITO | L217: Indefinido | M217: Ordinaria ART 22 | N217: Extensión de Beneficio Sindicato 1 | O217: mensual | P217: 42.5
... A222: 19.994.792-3 | B222: Inactivo | C222: Garay Rojas Diego Ignacio | D222: F-3oct25 | E222: M | F222: 45943 | G222: 36043 | H222: 998816408 | I222: ROOMS | J222: PUBLIC AREAS | K222: ASEADOR (A) /OPERARIO DE LAVANDERIA | L222: Plazo fijo | M222: Ordinaria ART 22 | N222: Extensión de Beneficio Sindicato 2 | O222: mensual | P222: 42.5
A223: 8.952.862-3 | B223: Activo | C223: Dehnhardt Ormeño David Alejandro | D223: F1 | E223: M | F223: 45026 | G223: 27300 | H223: 977066442 | I223: F&B ADM | J223: F&B ADMINISTRATION | K223: DIRECTOR FOOD & BEVERAGE | L223: Indefinido | M223: Exenta ART 22 | O223: mensual | P223: 42.5
A224: 21.774.085-1 | B224: Inactivo | C224: Jamed Cabezas Amanda Francisca | D224: F-1oct25 | E224: F | F224: 45934 | G224: 38396 | H224: 971085903 | I224: ROOMS | J224: GUEST SERVICES AGENT | K224: GUEST SERVICE AGENT | L224: Plazo fijo | M224: Ordinaria ART 22 | N224: Extensión de Beneficio Sindicato 2 | O224: mensual | P224: 42.5
A225: 22.386.150-4 | B225: Inactivo | C225: Ravanal Orellana Angel Del Piero | D225: F-4oct25 | E225: M | F225: 45950 | G225: 39191 | H225: 974681406 | I225: ROOMS | J225: AMA DE LLAVES | K225: Lencera (o) | L225: Plazo fijo | M225: Ordinaria ART 22 | N225: Extensión de Beneficio Sindicato 2 | O225: diaria | P225: 42.5
A226: 18.443.563-2 | B226: Activo | C226: Vidal Cerecer Pablo Antonio | D226: F-4oct25 | E226: M | F226: 45950 | G226: 34156 | H226: 982577080 | I226: ADMINISTRACION Y GERENCIA | J226: PREVENCION DE RIESGOS | K226: PREVENCIONISTA DE RIESGOS | L226: Plazo fijo | M226: Ordinaria ART 22 | N226: Extensión de Beneficio Sindicato 1 | O226: mensual | P226: 42.5
A227: 9.715.305-1 | B227: Activo | C227: Troncoso Latorre Maybett Del Carmen | D227: F-4oct25 | E227: F | F227: 45952 | G227: 25776 | H227: 942060223 | I227: ROOMS | J227: PUBLIC AREAS | K227: ASEADOR (A) /OPERARIO DE LAVANDERIA | L227: Plazo fijo | M227: Ordinaria ART 22 | N227: Extensión de Beneficio Sindicato 2 | O227: mensual | P227: 42.5
A228: 19.824.335-3 | B228: Activo | C228: Mardones Melo Esteban Elias | D228: F-4oct25 | E228: M | F228: 45952 | G228: 36036 | H228: 932964723 | I228: F&B | J228: ROOM SERVICE | K228: GARZON/CAJERO OUTLETS | L228: Plazo fijo | M228: Ordinaria ART 22 | N228: Extensión de Beneficio Sindicato 1 | O228: mensual | P228: 42.5
A229: 21.980.969-7 | B229: Activo | C229: Contreras Gallardo Martin Ricardo | D229: F-4oct25 | E229: M | F229: 45951 | G229: 38673 | H229: 942824175 | I229: MEMO | J229: PALAFITO | K229: COMMIS | L229: Plazo fijo | M229: Ordinaria ART 22 | N229: Extensión de Beneficio Sindicato 2 | O229: mensual | P229: 42.5
A230: 21.090.054-3 | B230: Inactivo | C230: Inostroza Vidal Cristóbal Francisco | D230: F-4oct25 | E230: M | F230: 45952 | G230: 37423 | H230: 930937041 | I230: F&B | J230: BANQUETES SERVICE | K230: ASEADOR/GUARDARROPIA | L230: Plazo fijo | M230: Ordinaria ART 22 | N230: Extensión de Beneficio Sindicato 2 | O230: mensual | P230: 42.5
A231: 19.881.327-3 | B231: Inactivo | C231: Mendoza Gonzalez Edy Santiago | D231: F-4oct25 | E231: M | F231: 45951 | G231: 35927 | H231: 949393956 | I231: F&B | J231: BANQUETES SERVICE | K231: GARZON/SALONERO BANQUETES | L231: Plazo fijo | M231: Ordinaria ART 22 | N231: Extensión de Beneficio Sindicato 1 | O231: mensual | P231: 42.5
A232: 21.471.617-8 | B232: Activo | C232: Sotelo Rosales Samuel Andrés | D232: F-4oct25 | E232: M | F232: 45953 | G232: 37968 | H232: 971912943 | I232: ROOMS | J232: PUBLIC AREAS | K232: ASEADOR (A) /OPERARIO DE LAVANDERIA | L232: Plazo fijo | M232: Ordinaria ART 22 | N232: Extensión de Beneficio Sindicato 2 | O232: mensual | P232: 42.5
A233: 20.703.802-4 | B233: Activo | C233: Díaz Gatica Diego Alonso | D233: F-4oct25 | E233: M | F233: 45953 | G233: 36913 | H233: 995326767 | I233: ROOMS | J233: AMA DE LLAVES | K233: Operario Mini Bar | L233: Plazo fijo | M233: Ordinaria ART 22 | N233: Extensión de Beneficio Sindicato 1 | O233: mensual | P233: 42.5
A234: 18.097.808-9 | B234: Activo | C234: Achurra Castro Christopher Abraham Segundo | D234: F-4oct25 | E234: M | F234: 45953 | G234: 33751 | H234: 979983899 | I234: F&B | J234: BANQUETES SERVICE | K234: SUPERVISOR DE COCINA | L234: Plazo fijo | M234: Ordinaria ART 22 | N234: Extensión de Beneficio Sindicato 2 | O234: mensual | P234: 42.5
A235: 21.559.331-2 | B235: Activo | C235: Pinto Herrera Maria Cristina | D235: F-4oct25 | E235: F | F235: 45953 | G235: 38101 | H235: 963867755 | I235: F&B | J235: COCINA | K235: COMMIS | L235: Plazo fijo | M235: Ordinaria ART 22 | N235: Extensión de Beneficio Sindicato 1 | O235: mensual | P235: 42.5
... A273: 21.086.273-0 | B273: Inactivo | C273: Vasquez Pino Daniela Valentina | D273: F-5oct25 | E273: F | F273: 45957 | G273: 37478 | H273: 934631748 | I273: F&B | J273: CID | K273: HOSTESS | L273: Plazo fijo | M273: Ordinaria ART 22 | N273: Extensión de Beneficio Sindicato 2 | O273: mensual | P273: 42.5
A274: 25.048.375-9 | B274: Activo | C274: Prado Fernandez Martin Esteban | D274: F1 | E274: M | F274: 42021 | G274: 27163 | H274: 984395989 | I274: VENTAS Y MARKETING | J274: REVENUE MANAGEMENT | K274: DIRECTOR OF REVENUE MANAGEMENT | L274: Indefinido | M274: Exenta ART 22 | O274: mensual | P274: 42.5
A275: 8.547.258-5 | B275: Activo | C275: Mondaca Cofre Luis Esteban | D275: F1 | E275: M | F275: 45352 | G275: 23323 | H275: 978652777 | I275: ADMINISTRACION Y GERENCIA | J275: GERENCIA GENERAL | K275: GERENTE GENERAL | L275: Indefinido | M275: Exenta ART 22 | O275: mensual | P275: 42.5
A276: 12.883.097-9 | B276: Inactivo | C276: Iriondo Nicoletti Maria Begoña | D276: F1 | E276: F | F276: 40406 | G276: 27555 | H276: 988189561 | I276: VENTAS Y MARKETING | J276: VENTAS | K276: DIRECTOR DE VENTAS Y MARKETING | L276: Indefinido | M276: Exenta ART 22 | O276: mensual | P276: 42.5
A277: 13.977.516-3 | B277: Activo | C277: Sanchez Corey Juan Pablo | D277: F1 | E277: M | F277: 41356 | G277: 29816 | H277: 965968209 | I277: ADMINISTRACION Y GERENCIA | J277: RECURSOS HUMANOS | K277: DIRECTOR DE RECURSOS HUMANOS | L277: Indefinido | M277: Exenta ART 22 | O277: mensual | P277: 42.5
A278: 15.328.347-8 | B278: Activo | C278: Pino Labra Paola Ivonne | D278: F1 | E278: F | F278: 40739 | G278: 30194 | H278: 940070703 | I278: ADMINISTRACION Y GERENCIA | J278: CONTRALORIA | K278: DIRECTOR DE FINANZAS | L278: Indefinido | M278: Exenta ART 22 | O278: mensual | P278: 42.5
A279: 17.017.379-1 | B279: Activo | C279: Velasquez Inostroza Sergio Felipe | D279: F1 | E279: M | F279: 45544 | G279: 32531 | H279: 942936954 | I279: ROOMS | J279: FRONT OFFICE ADMINISTRATION | K279: DIRECTOR DE HABITACIONES | L279: Indefinido | M279: Exenta ART 22 | O279: mensual | P279: 44
A280: 12.184.674-8 | B280: Activo | C280: Torres Herrera Patricia Del Pilar | D280: F1 | E280: F | F280: 45659 | G280: 26597 | H280: 992197502 | I280: MEMO | J280: ENTRENAMIENTO | K280: GERENTE DE CAPACITACIÓN Y CALIDAD | L280: Indefinido | M280: Exenta ART 22 | N280: Extensión de Beneficio Sindicato 1 | O280: mensual | P280: 44
A281: 10.987.144-3 | B281: Activo | C281: Paez Cabrera Carola Andrea | D281: F1 | E281: F | F281: 45659 | G281: 26377 | H281: 993258601 | I281: ROOMS | J281: HSKP - OTHERS | K281: GERENTE DE HOUSEKEEPING | L281: Indefinido | M281: Exenta ART 22 | N281: Extensión de Beneficio Sindicato 2 | O281: mensual | P281: 44
A282: 18.085.326-k | B282: Activo | C282: Aliaga Soto Sebastian Esteban | D282: F1 | E282: M | F282: 45733 | G282: 33682 | H282: 963708101 | I282: ROOMS | J282: HSKP - OTHERS | K282: Coordinador de Housekeeping | L282: Indefinido | M282: Ordinaria ART 22 | N282: Extensión de Beneficio Sindicato 2 | O282: mensual | P282: 42.5
A283: 18.049.437-5 | B283: Activo | C283: Yañez Rojas Jose Luis | D283: F1 | E283: M | F283: 41192 | G283: 33679 | H283: 950185594 | I283: F&B | J283: CID | K283: SUPERVISOR DE ALIMENTOS Y BEBIDAS | L283: Indefinido | M283: Ordinaria ART 22 | N283: Sindicato 1 | O283: mensual | P283: 42.5
A284: 25.621.831-3 | B284: Activo | C284: Zerpa Quintero Martin Jose | D284: F1 | E284: M | F284: 45622 | G284: 33221 | H284: 975446373 | I284: F&B | J284: CID | K284: SUPERVISOR DE ALIMENTOS Y BEBIDAS | L284: Indefinido | M284: Ordinaria ART 22 | N284: Sindicato 2 | O284: mensual | P284: 42.5
A285: 24.442.195-4 | B285: Activo | C285: Diaz Araos Leonardo David | D285: F1 | E285: M | F285: 45719 | G285: 37464 | H285: 945692870 | I285: ROOMS | J285: HSKP - OTHERS | K285: Supervisor de Housekeeping | L285: Indefinido | M285: Ordinaria ART 22 | N285: Sindicato 2 | O285: mensual | P285: 42.5
A286: 19.863.609-6 | B286: Activo | C286: Peña Moya Valeria Renee | D286: F1 | E286: F | F286: 45162 | G286: 36094 | H286: 959368009 | I286: F&B | J286: ROOM SERVICE | K286: SUPERVISOR DE ALIMENTOS Y BEBIDAS | L286: Indefinido | M286: Ordinaria ART 22 | N286: Sindicato 1 | O286: mensual | P286: 42.5
A287: 12.664.269-5 | B287: Activo | C287: Gonzalez Rojas Andres Benito | D287: F1 | E287: M | F287: 45474 | G287: 27072 | H287: 56968474432 | I287: INGENIERIA | J287: INGENIERIA | K287: DIRECTOR DE INGENIERIA | L287: Indefinido | M287: Exenta ART 22 | O287: mensual | P287: 42.5
A288: 25.953.048-2 | B288: Activo | C288: Soto Lugo Gustavo Adolfo | D288: F1 | E288: M | F288: 45672 | G288: 30594 | H288: 968056289 | I288: F&B | J288: OFICINA DE BANQUETES | K288: COORDINADOR(A) DE BANQUETES | L288: Indefinido | M288: Ordinaria ART 22 | N288: Sindicato 1 | O288: mensual | P288: 42.5
A289: 9.472.046-k | B289: Activo | C289: Moran Campos Sabina Del Carmen | D289: F1 | E289: F | F289: 45769 | G289: 22152 | H289: 952729496 | I289: ROOMS | J289: AMA DE LLAVES | K289: MUCAMA (O) /ASEADOR (A) /LENCERA (O) | L289: Indefinido | M289: Ordinaria ART 22 | N289: Sindicato 1 | O289: mensual | P289: 42.5
A290: 26.733.961-9 | B290: Activo | C290: Omaña Tirones Emilio Jose | D290: F1 | E290: M | F290: 44545 | G290: 32112 | H290: 979012898 | I290: VENTAS Y MARKETING | J290: VENTAS | K290: REPRESENTANTE DE VENTAS EBC | L290: Indefinido | M290: Exenta ART 22 | N290: Sindicato 1 | O290: mensual | P290: 42.5
A291: 18.515.077-1 | B291: Activo | C291: González Herrera Vanessa Del Carmen | D291: F1 | E291: F | F291: 45684 | G291: 34356 | H291: 973892142 | I291: F&B | J291: COCINA | K291: COMMIS | L291: Indefinido | M291: Ordinaria ART 22 | N291: Sindicato 2 | O291: mensual | P291: 42.5
A292: 13.917.528-k | B292: Activo | C292: Oses Ayala Cristian Marcelo | D292: F1 | E292: M | F292: 44896 | G292: 29460 | H292: 981435107 | I292: VENTAS Y MARKETING | J292: VENTAS | K292: REPRESENTANTE DE VENTAS EBC | L292: Indefinido | M292: Exenta ART 22 | N292: Sindicato 2 | O292: mensual | P292: 42.5
A293: 20.160.523-7 | B293: Activo | C293: Goldberg Woldarsky Alan Rodolfo | D293: F1 | E293: M | F293: 45404 | G293: 36628 | H293: 988198568 | I293: ADMINISTRACION Y GERENCIA | J293: CONTRALORIA | K293: Asistente de Finanzas | L293: Indefinido | M293: Ordinaria ART 22 | N293: Extensión de Beneficio Sindicato 2 | O293: mensual | P293: 42.5
A294: 20.207.982-2 | B294: Activo | C294: Morales Nonquepan Jessica Andrea | D294: F1 | E294: F | F294: 45117 | G294: 36479 | H294: 944586708 | I294: INGENIERIA | J294: INGENIERIA | K294: COORDINADOR DE MANTENCION | L294: Indefinido | M294: Ordinaria ART 22 | N294: Sindicato 2 | O294: mensual | P294: 42.5
A295: 14.613.243-k | B295: Activo | C295: Manriquez Montalva Daniela Valeska | D295: F1 | E295: F | F295: 45201 | G295: 29911 | H295: 978394219 | I295: ADMINISTRACION Y GERENCIA | J295: ENFERMERIA | K295: ENFERMERA | L295: Indefinido | M295: Ordinaria ART 22 | N295: Extensión de Beneficio Sindicato 1 | O295: mensual | P295: 42.5
A296: 17.489.336-5 | B296: Activo | C296: Contreras Salazar Francisco Ramon | D296: F1 | E296: M | F296: 45139 | G296: 33131 | H296: 958738222 | I296: F&B | J296: COCINA | K296: CHEF DE PARTIE | L296: Indefinido | M296: Ordinaria ART 22 | N296: Sindicato 1 | O296: mensual | P296: 42.5
A297: 19.276.711-3 | B297: Activo | C297: Dominguez Hernandez Marlene Delourdes | D297: F1 | E297: F | F297: 42287 | G297: 34936 | H297: 975623280 | I297: F&B | J297: COCINA | K297: CHEF DE PARTIE | L297: Indefinido | M297: Ordinaria ART 22 | N297: Sindicato 2 | O297: mensual | P297: 42.5
A298: 26.960.036-5 | B298: Activo | C298: Hernandez Hernandez Diego Rafael | D298: F1 | E298: M | F298: 45083 | G298: 30570 | H298: 936845757 | I298: INGENIERIA | J298: INGENIERIA | K298: TECNICO DE SERVICIOS GENERALES | L298: Indefinido | M298: Ordinaria ART 22 | N298: Sindicato 1 | O298: mensual | P298: 42.5
A299: 19.341.198-3 | B299: Activo | C299: Hasson Diaz Denisse Andrea | D299: F1 | E299: F | F299: 44561 | G299: 35087 | H299: 951339431 | I299: ROOMS | J299: GROOMS | K299: PORTERO/GROOM | L299: Indefinido | M299: Ordinaria ART 22 | N299: Sindicato 1 | O299: mensual | P299: 42.5
... A408: 20.453.033-5 | B408: Activo | C408: Moraga Diaz Victor Alejandro | D408: F1 | E408: M | F408: 45108 | G408: 36681 | H408: 935299947 | I408: F&B | J408: LOBBY BAR | K408: SUPERVISOR DE ALIMENTOS Y BEBIDAS | L408: Indefinido | M408: Ordinaria ART 22 | N408: Sindicato 1 | O408: mensual | P408: 42.5
A409: 21.010.433-k | B409: Inactivo | C409: Valenzuela Morales Catalina Andrea | D409: F-5oct25 | E409: F | F409: 45959 | G409: 37385 | H409: 977292815 | I409: ROOMS | J409: GUEST SERVICES AGENT | K409: GUEST SERVICE AGENT | L409: Plazo fijo | M409: Parcial ART 40 BIS | O409: diaria | P409: 20
A410: 21.355.332-1 | B410: Inactivo | C410: Monroy Herrera Edelein Jeannette | D410: F-5oct25 | E410: F | F410: 45960 | G410: 37830 | H410: 944708189 | I410: ROOMS | J410: GUEST SERVICES AGENT | K410: GUEST SERVICE AGENT | L410: Plazo fijo | M410: Parcial ART 40 BIS | O410: diaria | P410: 20
A411: 21.065.673-1 | B411: Inactivo | C411: Hidalgo Vasquez Bastian Eduardo | D411: F-1nov2025 | E411: M | F411: 45964 | G411: 37438 | H411: 946569580 | I411: F&B | J411: BANQUETES SERVICE | K411: GARZON/SALONERO BANQUETES | L411: Plazo fijo | M411: Parcial ART 40 BIS | O411: hora | P411: 30
A412: 21.976.707-2 | B412: Inactivo | C412: Escares Carranza Alondra Damaris Loretto | D412: F-1nov2025 | E412: F | F412: 45964 | G412: 38666 | H412: 957025677 | I412: F&B | J412: BANQUETES SERVICE | K412: GARZON/SALONERO BANQUETES | L412: Plazo fijo | M412: Parcial ART 40 BIS | O412: hora | P412: 30
A413: 22.458.381-8 | B413: Inactivo | C413: Ibañez Huaman Nalleli Brillid | D413: F-1nov25 | E413: F | F413: 45962 | G413: 39285 | H413: 984553612 | I413: ROOMS | J413: GROOMS | K413: PORTERO/GROOM | L413: Plazo fijo | M413: Ordinaria ART 22 | O413: diaria | P413: 20
A414: 26.387.023-9 | B414: Inactivo | C414: Muscadin - Stevenson | D414: F-1nov25 | E414: M | F414: 45962 | G414: 38257 | H414: 935069781 | I414: ROOMS | J414: PUBLIC AREAS | K414: ASEADOR (A) /OPERARIO DE LAVANDERIA | L414: Plazo fijo | M414: Ordinaria ART 22 | N414: Extensión de Beneficio Sindicato 1 | O414: diaria | P414: 20
A415: 17.479.678-5 | B415: Inactivo | C415: Birchmeier Shaw Ingeborg Patsy | D415: F-1nov25 | E415: F | F415: 45962 | G415: 32985 | H415: 984310408 | I415: ROOMS | J415: AMA DE LLAVES | K415: MUCAMA (O) /ASEADOR (A) /LENCERA (O) | L415: Plazo fijo | M415: Ordinaria ART 22 | N415: Extensión de Beneficio Sindicato 1 | O415: diaria | P415: 20
A416: 13.031.547-k | B416: Inactivo | C416: Velasquez Estay Denis Claudio | D416: F-1nov2025 | E416: M | F416: 45958 | G416: 27895 | H416: 979801524 | I416: F&B | J416: BANQUETES SERVICE | K416: PLAQUECERO | L416: Plazo fijo | M416: Parcial ART 40 BIS | O416: hora | P416: 30
A417: 20.239.534-1 | B417: Inactivo | C417: Andreotti Andreotti Owen Stuart | D417: F-1nov2025 | E417: M | F417: 45957 | G417: 36342 | H417: 910101697 | I417: F&B | J417: BANQUETES SERVICE | K417: PLAQUECERO | L417: Plazo fijo | M417: Parcial ART 40 BIS | O417: hora | P417: 30
A418: 28.108.465-8 | B418: Inactivo | C418: Alfred - Soimene | D418: F-1nov2025 | E418: F | F418: 45957 | G418: 38368 | H418: 927145029 | I418: F&B | J418: BANQUETES SERVICE | K418: PLAQUECERO | L418: Plazo fijo | M418: Parcial ART 40 BIS | O418: hora | P418: 30
A419: 16.791.116-1 | B419: Inactivo | C419: Melendez Marambio Maria Jose | D419: F-1nov2025 | E419: F | F419: 45962 | G419: 32398 | H419: 978955947 | I419: F&B | J419: BANQUETES SERVICE | K419: PLAQUECERO | L419: Plazo fijo | M419: Parcial ART 40 BIS | O419: hora | P419: 20
A420: 21.274.257-0 | B420: Activo | C420: Cabezas Villalon Emilia Afife | D420: F-1nov25 | E420: F | F420: 45964 | G420: 37713 | H420: 936300183 | I420: F&B | J420: CID | K420: HOSTESS | L420: Plazo fijo | M420: Ordinaria ART 22 | N420: Extensión de Beneficio Sindicato 2 | O420: mensual | P420: 42.5
A421: 21.392.465-6 | B421: Activo | C421: Moreno Rojas Genesis Fernanda | D421: F-1nov25 | E421: F | F421: 45964 | G421: 37879 | H421: 946962558 | I421: F&B | J421: COCINA | K421: COMMIS | L421: Plazo fijo | M421: Ordinaria ART 22 | N421: Extensión de Beneficio Sindicato 2 | O421: mensual | P421: 42.5
A422: 21.727.260-2 | B422: Activo | C422: Saldívar Pino Carolina Andrea | D422: F-1nov25 | E422: F | F422: 45964 | G422: 38335 | H422: 931275924 | I422: F&B | J422: COCINA | K422: COMMIS | L422: Plazo fijo | M422: Ordinaria ART 22 | N422: Extensión de Beneficio Sindicato 2 | O422: mensual | P422: 42.5
A423: 20.679.063-6 | B423: Inactivo | C423: Escobar González Diego Andrés | D423: F1nov2025 | E423: M | F423: 45964 | G423: 37082 | H423: 56984188712 | I423: F&B | J423: BANQUETES SERVICE | K423: GARZON/SALONERO BANQUETES | L423: Plazo fijo | M423: Parcial ART 40 BIS | O423: hora | P423: 30
A424: 20.053.299-6 | B424: Inactivo | C424: Carmona Vasquez Yanira Belen | D424: F-1nov25 | E424: F | F424: 45962 | G424: 36153 | H424: 971380294 | I424: MINOR | J424: GIMNASIO | K424: GUEST SERVICE AGENT | L424: Plazo fijo | M424: Ordinaria ART 22 | O424: diaria | P424: 20
A425: 21.823.057-1 | B425: Inactivo | C425: Poblete Poblete Angelina Ester | D425: F-1nov25 | E425: F | F425: 45962 | G425: 38457 | H425: 976073108 | I425: F&B | J425: LOUNGE | K425: GARZON/CAJERO OUTLETS | L425: Plazo fijo | M425: Ordinaria ART 22 | O425: diaria | P425: 20
A426: 20.923.218-9 | B426: Inactivo | C426: Nuñez Martinez Benjamin Andres | D426: F-1nov25 | E426: M | F426: 45962 | G426: 37236 | H426: 944652276 | I426: F&B | J426: COCINA | K426: COMMIS | L426: Plazo fijo | M426: Parcial ART 40 BIS | O426: diaria | P426: 20
A427: 21.643.913-9 | B427: Inactivo | C427: Rojas Romero Jessica Patricia | D427: F1nov2025 | E427: F | F427: 45965 | G427: 38223 | H427: 939528302 | I427: F&B | J427: BANQUETES SERVICE | K427: GARZON/SALONERO BANQUETES | L427: Plazo fijo | M427: Parcial ART 40 BIS | O427: hora | P427: 30
A428: 21.119.507-k | B428: Inactivo | C428: Sanhueza Fernández Cristóbal Emir | D428: F1nov2025 | E428: M | F428: 45965 | G428: 37532 | H428: 923807035 | I428: F&B | J428: BANQUETES SERVICE | K428: GARZON/SALONERO BANQUETES | L428: Plazo fijo | M428: Parcial ART 40 BIS | O428: hora | P428: 30
A429: 21.361.115-1 | B429: Inactivo | C429: Henríquez Araya Lissete Antonia | D429: F1nov2025 | E429: F | F429: 45965 | G429: 37842 | H429: 979043877 | I429: F&B | J429: BANQUETES SERVICE | K429: GARZON/SALONERO BANQUETES | L429: Plazo fijo | M429: Parcial ART 40 BIS | O429: hora | P429: 30
A430: 20.995.813-9 | B430: Inactivo | C430: Riffo Huiriqueo Benjamín Alexis | D430: F1nov2025 | E430: M | F430: 45965 | G430: 37345 | H430: 984297431 | I430: F&B | J430: BANQUETES SERVICE | K430: GARZON/SALONERO BANQUETES | L430: Plazo fijo | M430: Parcial ART 40 BIS | O430: hora | P430: 30
A431: 22.014.385-6 | B431: Inactivo | C431: Sariego Herrera Antonia Isidora Ignacia | D431: F1nov2025 | E431: M | F431: 45965 | G431: 38722 | H431: 946947293 | I431: F&B | J431: BANQUETES SERVICE | K431: GARZON/SALONERO BANQUETES | L431: Plazo fijo | M431: Parcial ART 40 BIS | O431: hora | P431: 30
A432: 20.055.229-6 | B432: Inactivo | C432: Villemaine Undurraga Janis Paz | D432: F1nov2025 | E432: F | F432: 45965 | G432: 36234 | H432: 9923730220 | I432: F&B | J432: BANQUETES SERVICE | K432: GARZON/SALONERO BANQUETES | L432: Plazo fijo | M432: Parcial ART 40 BIS | O432: hora | P432: 30
A433: 21.688.789-1 | B433: Inactivo | C433: Cuevas Roman Juan Pablo | D433: F1nov2025 | E433: M | F433: 45965 | G433: 38281 | H433: 973747472 | I433: F&B | J433: BANQUETES SERVICE | K433: GARZON/SALONERO BANQUETES | L433: Plazo fijo | M433: Parcial ART 40 BIS | O433: hora | P433: 30
A434: 21.932.176-7 | B434: Inactivo | C434: Torres Acuña Yaimara | D434: F-1nov2025 | E434: F | F434: 45965 | G434: 38610 | H434: 953616649 | I434: F&B | J434: BANQUETES SERVICE | K434: GARZON/SALONERO BANQUETES | L434: Plazo fijo | M434: Parcial ART 40 BIS | O434: hora | P434: 30
... A589: 21.767.032-2 | B589: Inactivo | C589: Hernandez Fuentealba Almendra Antonia | D589: F-1nov2025 | E589: F | F589: 45967 | G589: 38380 | H589: 962671722 | I589: F&B | J589: BANQUETES SERVICE | K589: GARZON/SALONERO BANQUETES | L589: Plazo fijo | M589: Parcial ART 40 BIS | O589: hora | P589: 30
A590: 21.405.413-2 | B590: Activo | C590: Barrera Ampuero Diego Israel | D590: F-1nov25 | E590: M | F590: 45966 | G590: 37888 | H590: 955246463 | I590: ADMINISTRACION Y GERENCIA | J590: SISTEMAS | K590: AUXILIAR DE SISTEMAS | L590: Plazo fijo | M590: Ordinaria ART 22 | N590: Extensión de Beneficio Sindicato 1 | O590: mensual | P590: 42.5
A591: 27.056.511-5 | B591: Inactivo | C591: Vallillo Rujano Diego Jesus | D591: F-1nov2025 | E591: M | F591: 45969 | G591: 38605 | H591: 966114174 | I591: F&B | J591: BANQUETES SERVICE | K591: GARZON/SALONERO BANQUETES | L591: Plazo fijo | M591: Parcial ART 40 BIS | O591: hora | P591: 30
A592: 21.329.542-k | B592: Inactivo | C592: Arellano Gonzalez Emilia Paz | D592: F-1nov2025 | E592: F | F592: 45969 | G592: 37818 | H592: 987042406 | I592: F&B | J592: BANQUETES SERVICE | K592: GARZON/SALONERO BANQUETES | L592: Plazo fijo | M592: Parcial ART 40 BIS | O592: hora | P592: 30
...

Sheet BAJAS NOVIEMBRE
A1: BAJAS DE NOVIEMBRE 2025
A4: Asociado - Número de Documento | B4: ESTADO | C4: Asociado - Estado | D4: Asociado - Código de Ficha | E4: Asociado - Nombre Completo | F4: Trabajo - Nombre Área Asignada(o) | G4: Trabajo - Nombre Sub-área Asignada(o) | H4: Trabajo - Cargo | I4: Trabajo - Fecha Ingreso Compañía | J4: Trabajo - Fecha Vencimiento Contrato | K4: Trabajo - Tipo de Contrato | L4: Trabajo - Tipo de Jornada | M4: Trabajo - Jornada Laboral | N4: Asociado - Forma de Pago | O4: Asociado - Banco | P4: Asociado - Tipo de Cuenta | Q4: Asociado - Número de Cuenta | R4: Trabajo - Fecha Término Trabajo | S4: Trabajo - Razón de Término | T4: Asociado - Fecha Pago de Finiquito | U4: Campos Personalizados de Asociado - Estado Finiquito | V4: Campos Personalizados de Asociado - Estado Finiquito | W4: Campos Personalizados de Asociado - Forma Pago Finiquito | X4: Campos Personalizados de Asociado - Fecha de Pago
A5: 24.753.417-2 | B5: =VLOOKUP(A5,'NOMINA DICIEMBRE'!A:Q,3,0) -> #N/A | C5: Inactivo | D5: F-3sep25 | E5: Velazquez Maria Eugenia | F5: =VLOOKUP(A5,'NOMINA OCTUBRE'!A:Q,9,0) -> MEMO | G5: =VLOOKUP(A5,'NOMINA OCTUBRE'!A:Q,10,0) -> PALAFITO | H5: =VLOOKUP(A5,'NOMINA OCTUBRE'!A:Q,11,0) -> AYUDANTE DE COCINA / PLAQUECERO | I5: 45915 | J5: 45973 | K5: Plazo fijo | L5: Ordinaria ART 22 | M5: mensual | N5: Transferencia Bancaria | O5: Santander | P5: Ahorro | Q5: 80626053 | R5: 45973 | S5: vencimiento_plazo | T5: 45975
A6: 20.388.609-8 | B6: =VLOOKUP(A6,'NOMINA DICIEMBRE'!A:Q,3,0) -> #N/A | C6: Inactivo | D6: F-3oct25 | E6: González Vásquez Xavier Alexander Ghary | F6: =VLOOKUP(A6,'NOMINA OCTUBRE'!A:Q,9,0) -> MEMO | G6: =VLOOKUP(A6,'NOMINA OCTUBRE'!A:Q,10,0) -> PALAFITO | H6: =VLOOKUP(A6,'NOMINA OCTUBRE'!A:Q,11,0) -> COMMIS | I6: 45948 | J6: 45985 | K6: Plazo fijo | L6: Ordinaria ART 22 | M6: mensual | N6: Transferencia Bancaria | O6: Banco Estado | P6: Vista | Q6: 20388609 | R6: 45974 | S6: renuncia | T6: 45982
A7: 18.936.748-1 | B7: =VLOOKUP(A7,'NOMINA DICIEMBRE'!A:Q,3,0) -> #N/A | C7: Inactivo | D7: F1 | E7: Acuña Alarcon Jose Pablo | F7: =VLOOKUP(A7,'NOMINA OCTUBRE'!A:Q,9,0) -> F&B | G7: =VLOOKUP(A7,'NOMINA OCTUBRE'!A:Q,10,0) -> OFICINA DE BANQUETES | H7: =VLOOKUP(A7,'NOMINA OCTUBRE'!A:Q,11,0) -> COORDINADOR(A) DE BANQUETES | I7: 43212 | K7: Indefinido | L7: Ordinaria ART 22 | M7: mensual | N7: Transferencia Bancaria | O7: Banco de Chile | P7: Corriente | Q7: 3631007608 | R7: 45971 | S7: renuncia | T7: 45974
A8: 19.994.792-3 | B8: =VLOOKUP(A8,'NOMINA DICIEMBRE'!A:Q,3,0) -> #N/A | C8: Inactivo | D8: F-3oct25 | E8: Garay Rojas Diego Ignacio | F8: =VLOOKUP(A8,'NOMINA OCTUBRE'!A:Q,9,0) -> ROOMS | G8: =VLOOKUP(A8,'NOMINA OCTUBRE'!A:Q,10,0) -> PUBLIC AREAS | H8: =VLOOKUP(A8,'NOMINA OCTUBRE'!A:Q,11,0) -> ASEADOR (A) /OPERARIO DE LAVANDERIA | I8: 45943 | J8: 45971 | K8: Plazo fijo | L8: Ordinaria ART 22 | M8: mensual | N8: Transferencia Bancaria | O8: Falabella | P8: Corriente | Q8: 19840072021 | R8: 45971 | S8: vencimiento_plazo | T8: 45975
A9: 19.664.249-8 | B9: =VLOOKUP(A9,'NOMINA DICIEMBRE'!A:Q,3,0) -> #N/A | C9: Inactivo | D9: F-4oct25 | E9: Martinez Beltran Victor Manuel | F9: =VLOOKUP(A9,'NOMINA OCTUBRE'!A:Q,9,0) -> ROOMS | G9: =VLOOKUP(A9,'NOMINA OCTUBRE'!A:Q,10,0) -> GUEST SERVICES AGENT | H9: =VLOOKUP(A9,'NOMINA OCTUBRE'!A:Q,11,0) -> GUEST SERVICE AGENT | I9: 45953 | J9: 45978 | K9: Plazo fijo | L9: Ordinaria ART 22 | M9: mensual | N9: Transferencia Bancaria | O9: Banco Estado | P9: Vista | Q9: 19664249 | R9: 45978 | S9: vencimiento_plazo | T9: 45982
A10: 24.210.636-9 | B10: =VLOOKUP(A10,'NOMINA DICIEMBRE'!A:Q,3,0) -> #N/A | C10: Inactivo | D10: F-4oct25 | E10: Ramos De La Cruz Judelka | F10: =VLOOKUP(A10,'NOMINA OCTUBRE'!A:Q,9,0) -> F&B | G10: =VLOOKUP(A10,'NOMINA OCTUBRE'!A:Q,10,0) -> LOBBY BAR | H10: =VLOOKUP(A10,'NOMINA OCTUBRE'!A:Q,11,0) -> GARZON/CAJERO OUTLETS | I10: 45953 | J10: 45985 | K10: Plazo fijo | L10: Ordinaria ART 22 | M10: mensual | N10: Transferencia Bancaria | O10: Ripley | P10: Corriente | Q10: 4012291559 | R10: 45985 | S10: vencimiento_plazo | T10: 45988
A11: 12.883.097-9 | B11: =VLOOKUP(A11,'NOMINA DICIEMBRE'!A:Q,3,0) -> #N/A | C11: Inactivo | D11: F1 | E11: Iriondo Nicoletti Maria Begoña | F11: =VLOOKUP(A11,'NOMINA OCTUBRE'!A:Q,9,0) -> VENTAS Y MARKETING | G11: =VLOOKUP(A11,'NOMINA OCTUBRE'!A:Q,10,0) -> VENTAS | H11: =VLOOKUP(A11,'NOMINA OCTUBRE'!A:Q,11,0) -> DIRECTOR DE VENTAS Y MARKETING | I11: 40406 | K11: Indefinido | L11: Exenta ART 22 | M11: mensual | N11: Transferencia Bancaria | O11: Scotiabank | P11: Corriente | Q11: 790100048036 | R11: 45982 | S11: necesidades_empresa | T11: 45988
A12: 22.458.381-8 | B12: =VLOOKUP(A12,'NOMINA DICIEMBRE'!A:Q,3,0) -> #N/A | C12: Inactivo | D12: F-1nov25 | E12: Ibañez Huaman Nalleli Brillid | F12: =VLOOKUP(A12,'NOMINA OCTUBRE'!A:Q,9,0) -> ROOMS | G12: =VLOOKUP(A12,'NOMINA OCTUBRE'!A:Q,10,0) -> GROOMS | H12: =VLOOKUP(A12,'NOMINA OCTUBRE'!A:Q,11,0) -> PORTERO/GROOM | I12: 45962 | J12: 45984 | K12: Plazo fijo | L12: Ordinaria ART 22 | M12: diaria | N12: Transferencia Bancaria | O12: Banco Estado | P12: Vista | Q12: 22458381 | R12: 45984 | S12: vencimiento_plazo | T12: 45988
A13: 19.646.384-4 | B13: =VLOOKUP(A13,'NOMINA DICIEMBRE'!A:Q,3,0) -> #N/A | C13: Inactivo | D13: F-2nov25 | E13: Venegas Yáñez Michelle Francisca | F13: F&B | G13: COCINA | H13: COMMIS | I13: 45971 | J13: 45994 | K13: Plazo fijo | L13: Ordinaria ART 22 | M13: mensual | N13: Transferencia Bancaria | O13: Falabella | P13: Corriente | Q13: 15840443994 | R13: 45980 | S13: renuncia | T13: 45982

Sheet ALTAS NOVIEMBRE
A1: ALTAS DE NOVIEMBRE 2025
B3: =VLOOKUP(A3,'NOMINA OCTUBRE'!A:P,3,0) -> #N/A
A4: Asociado - Número de Documento | B4: ESTADO | C4: Asociado - Nombre Completo | D4: Asociado - Código de Ficha | E4: Asociado - Sexo | F4: Trabajo - Fecha Ingreso Compañía | G4: Asociado - Fecha de Nacimiento | H4: Asociado - Teléfono Particular | I4: Trabajo - Nombre Área | J4: Trabajo - Nombre Sub-área Asignada(o) | K4: Trabajo - Cargo | L4: Trabajo - Tipo de Contrato | M4: Trabajo - Tipo de Jornada | N4: Trabajo - Sindicato | O4: Trabajo - Jornada Laboral | P4: Trabajo - Horas Semanales | Q4: Trabajo - Fecha Vencimiento Contrato
A5: 21.392.465-6 | B5: =VLOOKUP(A5,'NOMINA OCTUBRE'!A:P,3,0) -> #N/A | C5: Moreno Rojas Genesis Fernanda | D5: F-1nov25 | E5: F | F5: 45964 | G5: 37879 | H5: 946962558 | I5: F&B | J5: COCINA | K5: COMMIS | L5: Plazo fijo | M5: Ordinaria ART 22 | N5: Extensión de Beneficio Sindicato 2 | O5: mensual | P5: 42.5 | Q5: 45992
A6: 21.727.260-2 | B6: =VLOOKUP(A6,'NOMINA OCTUBRE'!A:P,3,0) -> #N/A | C6: Saldívar Pino Carolina Andrea | D6: F-1nov25 | E6: F | F6: 45964 | G6: 38335 | H6: 931275924 | I6: F&B | J6: COCINA | K6: COMMIS | L6: Plazo fijo | M6: Ordinaria ART 22 | N6: Extensión de Beneficio Sindicato 2 | O6: mensual | P6: 42.5 | Q6: 45992
A7: 20.825.173-2 | B7: =VLOOKUP(A7,'NOMINA OCTUBRE'!A:P,3,0) -> #N/A | C7: Adonis Lopez Chriss Ralfh | D7: F-2nov25 | E7: M | F7: 45971 | G7: 37101 | H7: 998715872 | I7: F&B | J7: LOBBY BAR | K7: GARZON/CAJERO OUTLETS | L7: Plazo fijo | M7: Ordinaria ART 22 | N7: Extensión de Beneficio Sindicato 1 | O7: mensual | P7: 42.5 | Q7: 46034
A8: 21.262.615-5 | B8: =VLOOKUP(A8,'NOMINA OCTUBRE'!A:P,3,0) -> #N/A | C8: Vergara Varas Gabriel Ignacio | D8: F-2nov25 | E8: M | F8: 45971 | G8: 37702 | H8: 933903480 | I8: F&B | J8: CID | K8: GARZON/CAJERO OUTLETS | L8: Plazo fijo | M8: Ordinaria ART 22 | N8: Extensión de Beneficio Sindicato 1 | O8: mensual | P8: 42.5 | Q8: 46027
A9: 20.450.016-9 | B9: =VLOOKUP(A9,'NOMINA OCTUBRE'!A:P,3,0) -> #N/A | C9: Álvarez Álvarez Carolain Belén | D9: F-2nov25 | E9: F | F9: 45971 | G9: 36755 | H9: 976846086 | I9: F&B | J9: COCINA | K9: COMMIS | L9: Plazo fijo | M9: Parcial ART 40 BIS | N9: Extensión de Beneficio Sindicato 2 | O9: mensual | P9: 42.5 | Q9: 45994
A10: 19.646.384-4 | B10: =VLOOKUP(A10,'NOMINA OCTUBRE'!A:P,3,0) -> #N/A | C10: Venegas Yáñez Michelle Francisca | D10: F-2nov25 | E10: F | F10: 45971 | G10: 35515 | H10: 975561071 | I10: F&B | J10: COCINA | K10: COMMIS | L10: Plazo fijo | M10: Ordinaria ART 22 | N10: Extensión de Beneficio Sindicato 1 | O10: mensual | P10: 42.5 | Q10: 45994
A11: 21.054.151-9 | B11: =VLOOKUP(A11,'NOMINA OCTUBRE'!A:P,3,0) -> #N/A | C11: Alvial Poza Benjamín Enoc | D11: F-2nov25 | E11: M | F11: 45971 | G11: 37543 | H11: 940540494 | I11: F&B | J11: COCINA | K11: COMMIS | L11: Plazo fijo | M11: Ordinaria ART 22 | N11: Extensión de Beneficio Sindicato 1 | O11: mensual | P11: 42.5 | Q11: 45994
A12: 25.647.366-6 | B12: =VLOOKUP(A12,'NOMINA OCTUBRE'!A:P,3,0) -> #N/A | C12: Reyes Montenegro Jose Javier | D12: F-2nov25 | E12: M | F12: 45971 | G12: 32561 | H12: 987210254 | I12: F&B | J12: OFICINA DE BANQUETES | K12: COORDINADOR(A) DE BANQUETES | L12: Plazo fijo | M12: Ordinaria ART 22 | N12: Extensión de Beneficio Sindicato 1 | O12: mensual | P12: 42.5 | Q12: 46001
A13: 27.395.783-9 | B13: =VLOOKUP(A13,'NOMINA OCTUBRE'!A:P,3,0) -> #N/A | C13: Lozano Peñaloza Breitner | D13: F-2nov25 | E13: M | F13: 45971 | G13: 34972 | H13: 979742233 | I13: F&B | J13: LOBBY BAR | K13: BARTENDER | L13: Plazo fijo | M13: Ordinaria ART 22 | N13: Extensión de Beneficio Sindicato 2 | O13: mensual | P13: 42.5 | Q13: 45994
A14: 18.539.959-1 | B14: =VLOOKUP(A14,'NOMINA OCTUBRE'!A:P,3,0) -> #N/A | C14: Rojas Jimenez Isidora Nicole | D14: F-2nov25 | E14: F | F14: 45971 | G14: 34164 | H14: 957651598 | I14: F&B | J14: LOBBY BAR | K14: BARTENDER | L14: Plazo fijo | M14: Ordinaria ART 22 | N14: Extensión de Beneficio Sindicato 2 | O14: mensual | P14: 42.5 | Q14: 45994
A15: 19.515.921-1 | B15: =VLOOKUP(A15,'NOMINA OCTUBRE'!A:P,3,0) -> #N/A | C15: Valencia Cárdenas Javier Ignacio | D15: F-2nov25 | E15: M | F15: 45971 | G15: 35345 | H15: 921679075 | I15: F&B | J15: LOBBY BAR | K15: BARTENDER | L15: Plazo fijo | M15: Ordinaria ART 22 | N15: Extensión de Beneficio Sindicato 1 | O15: mensual | P15: 42.5 | Q15: 45994
A16: 20.053.329-1 | B16: =VLOOKUP(A16,'NOMINA OCTUBRE'!A:P,3,0) -> #N/A | C16: Riveros Echeverría Catalina Valentina | D16: F-2nov25 | E16: F | F16: 45971 | G16: 36147 | H16: 955159745 | I16: F&B | J16: OFICINA DE BANQUETES | K16: Asistente de Eventos | L16: Plazo fijo | M16: Ordinaria ART 22 | N16: Extensión de Beneficio Sindicato 1 | O16: mensual | P16: 42.5 | Q16: 46001
A17: 11.166.190-1 | B17: =VLOOKUP(A17,'NOMINA OCTUBRE'!A:P,3,0) -> #N/A | C17: Artigas Espejo Francis Myriam | D17: F-4nov25 | E17: F | F17: 45985 | G17: 24510 | H17: 931973696 | I17: ROOMS | J17: AMA DE LLAVES | K17: MUCAMA (O) /ASEADOR (A) /LENCERA (O) | L17: Plazo fijo | M17: Ordinaria ART 22 | N17: Extensión de Beneficio Sindicato 1 | O17: mensual | P17: 42.5 | Q17: 46015

Sheet NOMINA DICIEMBRE
A1: PEGAR REPORTE " DAILY REPORTE DE BUK " DEL MES VIGENTE
A2: MOVER LA COLUMNA DE NUMERO DE DOCUMENTO AL INICIO
A3: ELIMINAR COLUMNA SUELDO BASE
A4: ELIMINAR COLUMNA Haberes No Imponibles - Movilización
A5: ELIMINAR COLUMNA CENTRO COSTOS Y ADICIONALES
A7: Asociado - Número de Documento | B7: Asociado - Estado | C7: Asociado - Nombre Completo | D7: Asociado - Código de Ficha | E7: Asociado - Sexo | F7: Trabajo - Fecha Ingreso Compañía | G7: Asociado - Fecha de Nacimiento | H7: Asociado - Teléfono Particular | I7: Trabajo - Nombre Área | J7: Trabajo - Nombre Sub-área Asignada(o) | K7: Trabajo - Cargo | L7: Trabajo - Tipo de Contrato | M7: Trabajo - Tipo de Jornada | N7: Trabajo - Sindicato | O7: Trabajo - Jornada Laboral | P7: Trabajo - Horas Semanales | Q7: Trabajo - Fecha Vencimiento Contrato
A8: 23.816.541-5 | B8: Activo | C8: Pecovnik Cortes Igor | D8: F1 | E8: M | F8: 42911 | G8: 26528 | H8: 999368991 | I8: ROOMS | J8: GROOMS | K8: Grooms/Portero/Valet | L8: Indefinido | M8: Ordinaria ART 22 | N8: Sindicato 1 | O8: mensual | P8: 42.5
A9: 19.894.223-5 | B9: Activo | C9: Faundez Vallejos Ailin Cricel | D9: F1 | E9: F | F9: 45740 | G9: 35733 | H9: 966647464 | I9: ADMINISTRACION Y GERENCIA | J9: SEGURIDAD | K9: GUARDIA | L9: Indefinido | M9: Ordinaria ART 22 | N9: Sindicato 1 | O9: mensual | P9: 44
A10: 19.429.624-k | B10: Activo | C10: Pons Valenzuela Fernanda Edith | D10: F1 | E10: F | F10: 45733 | G10: 35314 | H10: 957168583 | I10: F&B | J10: COCINA | K10: COMMIS | L10: Indefinido | M10: Ordinaria ART 22 | N10: Sindicato 1 | O10: mensual | P10: 42.5
A11: 25.399.125-9 | B11: Activo | C11: Seljak Piña Franz Isidro | D11: F1 | E11: F | F11: 45698 | G11: 34083 | H11: 958147239 | I11: F&B | J11: COCINA | K11: CHEF DE PARTIE | L11: Indefinido | M11: Ordinaria ART 22 | N11: Sindicato 1 | O11: mensual | P11: 42.5
A12: 19.837.527-6 | B12: Activo | C12: Troncoso Enriquez Luis David | D12: F1 | E12: M | F12: 45873 | G12: 35732 | H12: 965198972 | I12: ROOMS | J12: GUEST SERVICES AGENT | K12: GUEST SERVICE AGENT | L12: Indefinido | M12: Ordinaria ART 22 | N12: Extensión de Beneficio Sindicato 2 | O12: mensual | P12: 42.5
A13: 10.234.877-k | B13: Activo | C13: Salas Villaceca David Antonio | D13: F1 | E13: M | F13: 38153 | G13: 23601 | H13: 988189560 | I13: ADMINISTRACION Y GERENCIA | J13: CONTRALORIA | K13: CAJERO CENTRAL/COBRADOR | L13: Indefinido | M13: Exenta ART 22 | N13: Extensión de Beneficio Sindicato 1 | O13: mensual | P13: 42.5
A14: 17.924.524-8 | B14: Activo | C14: Marinao Cid Gabriel Isaías | D14: F1 | E14: M | F14: 45810 | G14: 33394 | H14: 926220231 | I14: ADMINISTRACION Y GERENCIA | J14: SEGURIDAD | K14: GUARDIA | L14: Indefinido | M14: Ordinaria ART 22 | N14: Sindicato 1 | O14: mensual | P14: 44
A15: 21.286.136-7 | B15: Activo | C15: Fieldhouse Reyes Alonso Emilio | D15: F1 | E15: M | F15: 45864 | G15: 37736 | H15: 965773140 | I15: ROOMS | J15: GUEST SERVICES AGENT | K15: GUEST SERVICE AGENT | L15: Indefinido | M15: Ordinaria ART 22 | N15: Sindicato 1 | O15: mensual | P15: 42.5
A16: 9.608.528-1 | B16: Activo | C16: Sepulveda Veloso Javier Antonio | D16: F1 | E16: M | F16: 45356 | G16: 23263 | H16: 997339466 | I16: ADMINISTRACION Y GERENCIA | J16: SEGURIDAD | K16: GUARDIA | L16: Indefinido | M16: Ordinaria ART 22 | N16: Sindicato 1 | O16: mensual | P16: 44
A17: 11.666.268-k | B17: Activo | C17: Zambrano Mandiola Bernarda Julia | D17: F1 | E17: F | F17: 45821 | G17: 25728 | H17: 939582128 | I17: ROOMS | J17: AMA DE LLAVES | K17: MUCAMA (O) /ASEADOR (A) /LENCERA (O) | L17: Indefinido | M17: Ordinaria ART 22 | N17: Sindicato 2 | O17: mensual | P17: 42.5
A18: 26.432.526-9 | B18: Activo | C18: Shephard Matos Francia Elizabeth | D18: F1 | E18: F | F18: 45815 | G18: 29055 | H18: 950352960 | I18: ROOMS | J18: AMA DE LLAVES | K18: MUCAMA (O) /ASEADOR (A) /LENCERA (O) | L18: Indefinido | M18: Ordinaria ART 22 | N18: Sindicato 2 | O18: mensual | P18: 42.5
A19: 20.673.002-1 | B19: Activo | C19: Roco Aguirre Enzo Valentino | D19: F1 | E19: M | F19: 45642 | G19: 36998 | H19: 922004346 | I19: ROOMS | J19: GUEST SERVICES AGENT | K19: GUEST SERVICE AGENT | L19: Indefinido | M19: Ordinaria ART 22 | N19: Sindicato 1 | O19: mensual | P19: 42.5
... A23: 16.373.482-6 | B23: Activo | C23: Fernández Gómez José Luis | D23: F1 | E23: M | F23: 45810 | G23: 31549 | H23: 967268112 | I23: ADMINISTRACION Y GERENCIA | J23: STORE COST CONTROL | K23: ENCARGADO DE BODEGA | L23: Indefinido | M23: Ordinaria ART 22 | N23: Sindicato 1 | O23: mensual | P23: 42.5
A24: 13.255.671-7 | B24: Activo | C24: Gómez Zenteno Rafael Andrés | D24: F-1ago25 | E24: M | F24: 45873 | G24: 28259 | H24: 951557885 | I24: VENTAS Y MARKETING | J24: DIPLOMATS | K24: Ejecutivo/a Diplomats | L24: Plazo fijo | M24: Ordinaria ART 22 | N24: Extensión de Beneficio Sindicato 2 | O24: mensual | P24: 42.5 | Q24: 46026
A25: 14.131.634-6 | B25: Activo | C25: Menchaca Fernández María Constanza | D25: F1 | E25: F | F25: 45803 | G25: 29666 | H25: 994358167 | I25: VENTAS Y MARKETING | J25: VENTAS | K25: EJECUTIVA DE VENTAS DE NUEVOS NEGOCIOS | L25: Indefinido | M25: Exenta ART 22 | N25: Extensión de Beneficio Sindicato 2 | O25: mensual | P25: 44
A26: 20.108.477-6 | B26: Activo | C26: Moreno Laso Vicente Daniel | D26: F1 | E26: M | F26: 45810 | G26: 36248 | H26: 942775139 | I26: ADMINISTRACION Y GERENCIA | J26: CONTRALORIA | K26: Auxiliar de Créditos | L26: Indefinido | M26: Ordinaria ART 22 | N26: Extensión de Beneficio Sindicato 2 | O26: mensual | P26: 42.5
A27: 20.761.204-9 | B27: Activo | C27: Parra Quezada Giulliana Stephani | D27: F1 | E27: F | F27: 45810 | G27: 37023 | H27: 939039706 | I27: ADMINISTRACION Y GERENCIA | J27: CONTRALORIA | K27: Auxiliar de Créditos | L27: Indefinido | M27: Ordinaria ART 22 | N27: Extensión de Beneficio Sindicato 1 | O27: mensual | P27: 42.5
A28: 10.807.412-4 | B28: Activo | C28: Sáez Barrios Jean Eric | D28: F1 | E28: M | F28: 45810 | G28: 28931 | H28: 968141966 | I28: VENTAS Y MARKETING | J28: VENTAS | K28: Ejecutivo de Cuentas Tour & Travel | L28: Indefinido | M28: Exenta ART 22 | N28: Extensión de Beneficio Sindicato 1 | O28: mensual | P28: 44
A29: 27.917.972-2 | B29: Activo | C29: Fernandez Mambuscay Julian Estiben | D29: F1 | E29: M | F29: 44972 | G29: 37092 | H29: 993010961 | I29: F&B | J29: STEWARD | K29: SUPERVISOR STEWARD | L29: Indefinido | M29: Ordinaria ART 22 | N29: Sindicato 1 | O29: mensual | P29: 42.5
A30: 26.409.239-6 | B30: Activo | C30: Anzola Villalon Juan Carlos | D30: F1 | E30: M | F30: 43608 | G30: 27715 | H30: 994905005 | I30: F&B | J30: STEWARD | K30: SUPERVISOR STEWARD | L30: Indefinido | M30: Ordinaria ART 22 | N30: Sindicato 1 | O30: mensual | P30: 42.5
A31: 28.184.786-4 | B31: Activo | C31: Feltran Loubens | D31: F1 | E31: M | F31: 45298 | G31: 34281 | H31: 936263836 | I31: F&B | J31: STEWARD | K31: SUPERVISOR STEWARD | L31: Indefinido | M31: Ordinaria ART 22 | N31: Sindicato 1 | O31: mensual | P31: 42.5
A32: 13.679.411-6 | B32: Activo | C32: Irarrazabal Contreras Sabrina Gisella | D32: F1 | E32: F | F32: 45266 | G32: 28879 | H32: 983037941 | I32: F&B | J32: CID | K32: BARTENDER | L32: Indefinido | M32: Ordinaria ART 22 | N32: Sindicato 1 | O32: mensual | P32: 42.5
A33: 17.217.358-6 | B33: Activo | C33: Borquez Venegas Mario Alejandro | D33: F1 | E33: M | F33: 45278 | G33: 32862 | H33: 56983577085 | I33: F&B | J33: LOBBY BAR | K33: BARTENDER | L33: Indefinido | M33: Ordinaria ART 22 | N33: Sindicato 1 | O33: mensual | P33: 42.5
A34: 19.292.167-8 | B34: Activo | C34: Martinez Pérez Francisca Andrea | D34: F1 | E34: F | F34: 45670 | G34: 35142 | H34: 936559107 | I34: F&B | J34: LOBBY BAR | K34: BARTENDER | L34: Indefinido | M34: Ordinaria ART 22 | N34: Sindicato 1 | O34: mensual | P34: 42.5
A35: 19.736.484-k | B35: Activo | C35: Arevalo Díaz Ignacio Alfonso | D35: F1 | E35: M | F35: 45666 | G35: 35747 | H35: 985013018 | I35: F&B | J35: LOBBY BAR | K35: BARTENDER | L35: Indefinido | M35: Ordinaria ART 22 | N35: Sindicato 1 | O35: mensual | P35: 42.5
A36: 20.059.173-9 | B36: Activo | C36: Medina Pino Amapola Belen | D36: F1 | E36: F | F36: 45683 | G36: 36273 | H36: 999858027 | I36: F&B | J36: LOBBY BAR | K36: BARTENDER | L36: Indefinido | M36: Ordinaria ART 22 | N36: Sindicato 1 | O36: mensual | P36: 42.5
... A56: 18.337.130-4 | B56: Activo | C56: Bernal Pizarro Diego Antonio | D56: F1 | E56: M | F56: 41649 | G56: 33919 | H56: 987452858 | I56: ADMINISTRACION Y GERENCIA | J56: STORE COST CONTROL | K56: RECEPCIONISTA DE MERCADERIA | L56: Indefinido | M56: Ordinaria ART 22 | N56: Sindicato 2 | O56: mensual | P56: 42.5
A57: 26.018.535-7 | B57: Activo | C57: Josema - Bettyna | D57: F-3ago25 | E57: F | F57: 45890 | G57: 37362 | H57: 928848614 | I57: F&B | J57: STEWARD | K57: PLAQUECERO | L57: Plazo fijo | M57: Ordinaria ART 22 | N57: Extensión de Beneficio Sindicato 1 | O57: mensual | P57: 42.5 | Q57: 46001
A58: 21.042.313-3 | B58: Activo | C58: Gonzalez Muñoz Diego Andres | D58: F-2sep25 | E58: M | F58: 45909 | G58: 37420 | H58: 930232989 | I58: F&B | J58: COCINA | K58: COMMIS | L58: Plazo fijo | M58: Ordinaria ART 22 | N58: Extensión de Beneficio Sindicato 1 | O58: mensual | P58: 42.5 | Q58: 46001
A59: 14.171.763-4 | B59: Activo | C59: Román Ferreira Susana Inés | D59: F-1sep25 | E59: F | F59: 45902 | G59: 29445 | H59: 950516210 | I59: F&B | J59: STEWARD | K59: PLAQUECERO | L59: Plazo fijo | M59: Ordinaria ART 22 | N59: Extensión de Beneficio Sindicato 2 | O59: mensual | P59: 42.5 | Q59: 46008
A60: 25.955.327-k | B60: Activo | C60: Delva - Yol Bine Mose Ricka | D60: F-3ago25 | E60: F | F60: 45890 | G60: 38371 | H60: 949833163 | I60: F&B | J60: STEWARD | K60: PLAQUECERO | L60: Plazo fijo | M60: Ordinaria ART 22 | N60: Extensión de Beneficio Sindicato 1 | O60: mensual | P60: 42.5 | Q60: 45999
A61: 18.637.768-0 | B61: Activo | C61: Bastías González María Jesús | D61: F-2oct25 | E61: F | F61: 45939 | G61: 34178 | H61: 974960934 | I61: F&B | J61: COCINA | K61: COMMIS | L61: Plazo fijo | M61: Ordinaria ART 22 | N61: Extensión de Beneficio Sindicato 1 | O61: mensual | P61: 42.5 | Q61: 45999
A62: 22.207.390-1 | B62: Activo | C62: Garrido Garro Martin Leandro | D62: F-4sep25 | E62: M | F62: 45927 | G62: 38969 | H62: 998954307 | I62: F&B | J62: COCINA | K62: COMMIS | L62: Plazo fijo | M62: Ordinaria ART 22 | N62: Extensión de Beneficio Sindicato 1 | O62: mensual | P62: 42.5 | Q62: 46003
A63: 21.271.915-3 | B63: Activo | C63: Gonzalez Jara Carla Pia | D63: F-4sep25 | E63: F | F63: 45925 | G63: 37705 | H63: 929053336 | I63: F&B | J63: COCINA | K63: COMMIS | L63: Plazo fijo | M63: Ordinaria ART 22 | N63: Extensión de Beneficio Sindicato 1 | O63: mensual | P63: 42.5 | Q63: 46001
A64: 17.811.830-7 | B64: Activo | C64: Carreaux Astudillo Daniela Scarlett | D64: F-5sep25 | E64: F | F64: 45929 | G64: 33587 | H64: 985058289 | I64: F&B | J64: STEWARD | K64: PLAQUECERO | L64: Plazo fijo | M64: Ordinaria ART 22 | N64: Extensión de Beneficio Sindicato 1 | O64: mensual | P64: 42.5 | Q64: 46008
A65: 25.519.267-1 | B65: Activo | C65: Henry - Bertha | D65: F-2oct25 | E65: F | F65: 45941 | G65: 33365 | H65: 932969731 | I65: F&B | J65: STEWARD | K65: PLAQUECERO | L65: Plazo fijo | M65: Ordinaria ART 22 | N65: Extensión de Beneficio Sindicato 1 | O65: mensual | P65: 42.5 | Q65: 46002
A66: 26.854.920-k | B66: Activo | C66: Romelus - Ralph | D66: F-2oct25 | E66: M | F66: 45942 | G66: 23475 | H66: 933593190 | I66: F&B | J66: STEWARD | K66: PLAQUECERO | L66: Plazo fijo | M66: Ordinaria ART 22 | N66: Extensión de Beneficio Sindicato 1 | O66: mensual | P66: 42.5 | Q66: 46003
A67: 28.423.153-8 | B67: Activo | C67: Rivera Mora Andy Joel | D67: F-2oct25 | E67: M | F67: 45936 | G67: 39036 | H67: 927625490 | I67: F&B | J67: LOBBY BAR | K67: GARZON/CAJERO OUTLETS | L67: Plazo fijo | M67: Ordinaria ART 22 | N67: Extensión de Beneficio Sindicato 1 | O67: mensual | P67: 42.5 | Q67: 46008
A68: 28.488.745-k | B68: Activo | C68: Vargas Pedraza Ronald Alonso | D68: F-3sep25 | E68: M | F68: 45919 | G68: 39013 | H68: 945885112 | I68: ROOMS | J68: PUBLIC AREAS | K68: ASEADOR (A) /OPERARIO DE LAVANDERIA | L68: Plazo fijo | M68: Ordinaria ART 22 | N68: Extensión de Beneficio Sindicato 2 | O68: mensual | P68: 42.5 | Q68: 46010
A69: 20.657.673-1 | B69: Activo | C69: Lopez Cornejo Claudia Belen | D69: F1 | E69: F | F69: 45673 | G69: 36908 | H69: 955359553 | I69: F&B | J69: CID | K69: GARZON/CAJERO OUTLETS | L69: Indefinido | M69: Ordinaria ART 22 | N69: Sindicato 1 | O69: mensual | P69: 42.5
A70: 26.008.888-2 | B70: Activo | C70: Ambroise - Faniel | D70: F-1sep25 | E70: M | F70: 45907 | G70: 30407 | H70: 936527566 | I70: F&B | J70: STEWARD | K70: PLAQUECERO | L70: Plazo fijo | M70: Ordinaria ART 22 | N70: Extensión de Beneficio Sindicato 1 | O70: mensual | P70: 42.5 | Q70: 46008
A71: 26.543.659-5 | B71: Activo | C71: Aceus - Gedson | D71: F1 | E71: M | F71: 45663 | G71: 36885 | H71: 948910429 | I71: F&B | J71: STEWARD | K71: PLAQUECERO | L71: Indefinido | M71: Ordinaria ART 22 | N71: Sindicato 1 | O71: mensual | P71: 42.5
A72: 19.902.051-k | B72: Activo | C72: Albornoz Cardenas Javiera Denisse | D72: F1 | E72: F | F72: 45318 | G72: 35860 | H72: 987075874 | I72: ROOMS | J72: GROOMS | K72: PORTERO/GROOM | L72: Indefinido | M72: Ordinaria ART 22 | N72: Sindicato 1 | O72: mensual | P72: 42.5
A73: 20.815.795-7 | B73: Activo | C73: Araya Ponce Topacio Esmeralda | D73: F1 | E73: F | F73: 45119 | G73: 37406 | H73: 991350510 | I73: F&B | J73: BANQUETES SERVICE | K73: GARZON/SALONERO BANQUETES | L73: Indefinido | M73: Ordinaria ART 22 | N73: Sindicato 2 | O73: mensual | P73: 42.5
A74: 26.132.065-7 | B74: Activo | C74: Brutus Salien | D74: F1 | E74: M | F74: 45109 | G74: 28857 | H74: 937098467 | I74: F&B | J74: STEWARD | K74: PLAQUECERO | L74: Indefinido | M74: Ordinaria ART 22 | N74: Sindicato 1 | O74: mensual | P74: 42.5
A75: 10.551.228-7 | B75: Activo | C75: Calderon Machuca Pedro Enrique | D75: F1 | E75: M | F75: 45632 | G75: 24032 | H75: 994138167 | I75: F&B | J75: STEWARD | K75: PLAQUECERO | L75: Indefinido | M75: Ordinaria ART 22 | N75: Sindicato 1 | O75: mensual | P75: 42.5
A76: 14.214.026-8 | B76: Activo | C76: Chamblas Aroca Jessica Beatriz | D76: F1 | E76: F | F76: 42524 | G76: 29615 | H76: 933770240 | I76: F&B | J76: STEWARD | K76: PLAQUECERO | L76: Indefinido | M76: Ordinaria ART 22 | N76: Sindicato 2 | O76: mensual | P76: 42.5
A77: 17.573.233-0 | B77: Activo | C77: Fuenzalida Valenzuela Luisa Cristina | D77: F1 | E77: F | F77: 45667 | G77: 33148 | H77: 931172681 | I77: F&B | J77: STEWARD | K77: PLAQUECERO | L77: Indefinido | M77: Ordinaria ART 22 | N77: Sindicato 2 | O77: mensual | P77: 42.5
A78: 19.161.061-k | B78: Activo | C78: Gonzalez Gomez Nicolas Ignacio | D78: F1 | E78: M | F78: 43374 | G78: 34826 | H78: 979359765 | I78: ROOMS | J78: GROOMS | K78: PORTERO/GROOM | L78: Indefinido | M78: Ordinaria ART 22 | N78: Sindicato 2 | O78: mensual | P78: 42.5
A79: 24.344.452-7 | B79: Activo | C79: Guerrero Aviles Genesis Endira | D79: F1 | E79: F | F79: 45368 | G79: 33541 | H79: 948526128 | I79: F&B | J79: BANQUETES SERVICE | K79: ASEADOR/GUARDARROPIA/LENCERA | L79: Indefinido | M79: Ordinaria ART 22 | N79: Sindicato 2 | O79: mensual | P79: 42.5
A80: 20.780.058-9 | B80: Activo | C80: Mallea Bravo Jacqueline Del Carmen | D80: F-1oct25 | E80: F | F80: 45931 | G80: 37057 | H80: 923877926 | I80: MINOR | J80: GIMNASIO | K80: GUEST SERVICE AGENT | L80: Plazo fijo | M80: Ordinaria ART 22 | N80: Extensión de Beneficio Sindicato 1 | O80: mensual | P80: 42.5 | Q80: 45999
A81: 17.413.209-7 | B81: Activo | C81: Mendez Correa Felipe Ignacio | D81: F1 | E81: M | F81: 44581 | G81: 32781 | H81: 931169919 | I81: F&B | J81: BANQUETES SERVICE | K81: GARZON/SALONERO BANQUETES | L81: Indefinido | M81: Ordinaria ART 22 | N81: Sindicato 2 | O81: mensual | P81: 42.5
A82: 25.849.345-1 | B82: Activo | C82: Montalvan Reyes Karla Patricia | D82: F1 | E82: F | F82: 45511 | G82: 36165 | H82: 982504891 | I82: ROOMS | J82: GROOMS | K82: PORTERO/GROOM | L82: Indefinido | M82: Ordinaria ART 22 | N82: Sindicato 1 | O82: mensual | P82: 42.5
A83: 9.830.027-9 | B83: Activo | C83: Mora Roa Maria Ines | D83: F1 | E83: F | F83: 45666 | G83: 22179 | H83: 991012570 | I83: F&B | J83: STEWARD | K83: PLAQUECERO | L83: Indefinido | M83: Ordinaria ART 22 | N83: Sindicato 2 | O83: mensual | P83: 42.5
A84: 20.187.012-7 | B84: Activo | C84: Moraga Piñeda Wladimir Esteban | D84: F1 | E84: M | F84: 45427 | G84: 36243 | H84: 941985142 | I84: F&B | J84: BANQUETES SERVICE | K84: GARZON/SALONERO BANQUETES | L84: Indefinido | M84: Ordinaria ART 22 | N84: Sindicato 2 | O84: mensual | P84: 42.5
A85: 7.640.380-5 | B85: Activo | C85: Rivera Diaz Leonardo Luis | D85: F1 | E85: M | F85: 45517 | G85: 21484 | H85: 965695282 | I85: ROOMS | J85: GROOMS | K85: PORTERO/GROOM | L85: Indefinido | M85: Ordinaria ART 22 | N85: Sindicato 1 | O85: mensual | P85: 42.5
A86: 27.827.497-7 | B86: Activo | C86: Roja Zapata Crisaida Carlina | D86: F1 | E86: F | F86: 45569 | G86: 28555 | H86: 944887678 | I86: F&B | J86: STEWARD | K86: PLAQUECERO | L86: Indefinido | M86: Ordinaria ART 22 | N86: Sindicato 1 | O86: mensual | P86: 42.5
A87: 25.561.840-7 | B87: Activo | C87: Zuñiga Cardenas Elizabeth | D87: F1 | E87: F | F87: 45303 | G87: 33128 | H87: 952100015 | I87: ROOMS | J87: AMA DE LLAVES | K87: MUCAMA/ASEADORA/OPERARIA DE LAVANDERIA | L87: Indefinido | M87: Ordinaria ART 22 | N87: Sindicato 2 | O87: mensual | P87: 42.5
A88: 21.193.707-6 | B88: Activo | C88: Ruminot Quiero Leandro Dunkant | D88: F1 | E88: M | F88: 45691 | G88: 37602 | H88: 958737321 | I88: MEMO | J88: ENTRENAMIENTO | K88: Auxiliar de Entrenamiento y Calidad | L88: Indefinido | M88: Ordinaria ART 22 | N88: Extensión de Beneficio Sindicato 1 | O88: mensual | P88: 42.5
A89: 20.051.674-5 | B89: Activo | C89: Gutierrez Figueroa Cynthia Valentina | D89: F1 | E89: F | F89: 45251 | G89: 36079 | H89: 996984580 | I89: F&B | J89: BANQUETES SERVICE | K89: BARTENDER | L89: Indefinido | M89: Ordinaria ART 22 | N89: Sindicato 1 | O89: mensual | P89: 42.5
A90: 25.405.487-9 | B90: Activo | C90: Astudillo Muñoz Dora Lilia | D90: F1 | E90: F | F90: 45573 | G90: 26305 | H90: 946483106 | I90: ADMINISTRACION Y GERENCIA | J90: SEGURIDAD | K90: GUARDIA | L90: Indefinido | M90: Ordinaria ART 22 | N90: Sindicato 1 | O90: mensual | P90: 44
A91: 15.360.241-7 | B91: Activo | C91: Caviedes Navarrete Maribel Margarita | D91: F1 | E91: F | F91: 45050 | G91: 27730 | H91: 933638035 | I91: ADMINISTRACION Y GERENCIA | J91: SEGURIDAD | K91: GUARDIA | L91: Indefinido | M91: Ordinaria ART 22 | N91: Sindicato 1 | O91: mensual | P91: 44
A92: 19.382.117-0 | B92: Activo | C92: Donoso Otarola Cindy Estefania | D92: F1 | E92: F | F92: 44518 | G92: 35160 | H92: 988784390 | I92: ADMINISTRACION Y GERENCIA | J92: SEGURIDAD | K92: GUARDIA | L92: Indefinido | M92: Ordinaria ART 22 | N92: Sindicato 1 | O92: mensual | P92: 44
... A119: 10.154.154-1 | B119: Activo | C119: Parada Morales Hermann Ives | D119: F1 | E119: M | F119: 40984 | G119: 23949 | H119: 989537589 | I119: ADMINISTRACION Y GERENCIA | J119: SEGURIDAD | K119: SENIOR DE SEGURIDAD | L119: Indefinido | M119: Ordinaria ART 22 | N119: Sindicato 1 | O119: mensual | P119: 44
A120: 27.881.210-3 | B120: Activo | C120: Diaz Arenas Luz Mary | D120: F-3oct25 | E120: F | F120: 45948 | G120: 32704 | H120: 989838933 | I120: MEMO | J120: PALAFITO | K120: PLAQUECERO(A)/COCINERO(A) | L120: Plazo fijo | M120: Ordinaria ART 22 | N120: Extensión de Beneficio Sindicato 1 | O120: mensual | P120: 42.5 | Q120: 45999
A121: 17.852.797-5 | B121: Activo | C121: Arriagada Oyarzun Guisselle Andrea | D121: F1 | E121: F | F121: 45258 | G121: 33558 | H121: 973277767 | I121: ROOMS | J121: HSKP - OTHERS | K121: SUPERVISOR | L121: Indefinido | M121: Ordinaria ART 22 | N121: Sindicato 2 | O121: mensual | P121: 42.5
A122: 21.012.024-6 | B122: Activo | C122: Basaure Boetto Gonzalo Matias | D122: F1 | E122: M | F122: 45329 | G122: 37383 | H122: 991209048 | I122: ROOMS | J122: GUEST SERVICES AGENT | K122: GUEST SERVICE AGENT | L122: Indefinido | M122: Ordinaria ART 22 | N122: Sindicato 1 | O122: mensual | P122: 42.5
A123: 22.804.464-4 | B123: Activo | C123: Catanach Tamara Margaret | D123: F1 | E123: F | F123: 45505 | G123: 33350 | H123: 973883722 | I123: MINOR | J123: GIMNASIO | K123: GUEST SERVICE AGENT | L123: Indefinido | M123: Ordinaria ART 22 | N123: Sindicato 1 | O123: mensual | P123: 42.5
A124: 25.419.493-k | B124: Activo | C124: Dol Stanley | D124: F1 | E124: M | F124: 42836 | G124: 33739 | H124: 979714376 | I124: ROOMS | J124: GUEST SERVICES AGENT | K124: GUEST SERVICE AGENT | L124: Indefinido | M124: Ordinaria ART 22 | N124: Sindicato 2 | O124: mensual | P124: 42.5
A125: 23.902.630-3 | B125: Activo | C125: Fernandez Nuñez Melissa Maria | D125: F1 | E125: F | F125: 45004 | G125: 32483 | H125: 963356701 | I125: ROOMS | J125: GUEST SERVICES AGENT | K125: GUEST SERVICE AGENT | L125: Indefinido | M125: Ordinaria ART 22 | N125: Sindicato 1 | O125: mensual | P125: 42.5
A126: 19.586.798-4 | B126: Activo | C126: Fica Matus Jose Ignacio | D126: F1 | E126: M | F126: 45078 | G126: 35685 | H126: 56961303270 | I126: ROOMS | J126: HSKP - OTHERS | K126: SUPERVISOR | L126: Indefinido | M126: Ordinaria ART 22 | N126: Sindicato 2 | O126: mensual | P126: 42.5
A127: 20.955.284-1 | B127: Activo | C127: Luna Salinas Valentina Millaray | D127: F1 | E127: F | F127: 45573 | G127: 37279 | H127: 957113557 | I127: ROOMS | J127: GUEST SERVICES AGENT | K127: GUEST SERVICE AGENT | L127: Indefinido | M127: Ordinaria ART 22 | N127: Sindicato 1 | O127: mensual | P127: 42.5
A128: 19.850.167-0 | B128: Activo | C128: Quezada Mella Catalina Isidora | D128: F1 | E128: F | F128: 45201 | G128: 35793 | H128: 968150689 | I128: ROOMS | J128: GUEST SERVICES AGENT | K128: GUEST SERVICE AGENT | L128: Indefinido | M128: Ordinaria ART 22 | N128: Sindicato 1 | O128: mensual | P128: 42.5
A129: 20.390.766-4 | B129: Activo | C129: Salamanca Fuentes Javiera Belen Esther | D129: F1 | E129: F | F129: 45475 | G129: 36655 | H129: 955212392 | I129: ROOMS | J129: GUEST SERVICES AGENT | K129: GUEST SERVICE AGENT | L129: Indefinido | M129: Ordinaria ART 22 | N129: Sindicato 2 | O129: mensual | P129: 42.5
A130: 19.643.215-9 | B130: Activo | C130: Valdes Torres Aline Tamara | D130: F1 | E130: F | F130: 45489 | G130: 35426 | H130: 987710109 | I130: ROOMS | J130: GUEST SERVICES AGENT | K130: GUEST SERVICE AGENT | L130: Indefinido | M130: Ordinaria ART 22 | N130: Sindicato 1 | O130: mensual | P130: 42.5
A131: 26.779.203-8 | B131: Activo | C131: Delgado Garcia Joselin Del Valle | D131: F1 | E131: F | F131: 45677 | G131: 31282 | H131: 945223360 | I131: ROOMS | J131: HSKP - OTHERS | K131: Supervisor de Housekeeping | L131: Indefinido | M131: Ordinaria ART 22 | N131: Sindicato 2 | O131: mensual | P131: 42.5
A132: 28.054.625-9 | B132: Activo | C132: Lozano Arevalo Hassler | D132: F1 | E132: M | F132: 45048 | G132: 33274 | H132: 939198559 | I132: ROOMS | J132: HSKP - OTHERS | K132: Supervisor de Housekeeping | L132: Indefinido | M132: Ordinaria ART 22 | N132: Sindicato 2 | O132: mensual | P132: 42.5
... A138: 15.511.414-2 | B138: Activo | C138: Chehuan Antileo Mario Roberto | D138: F1 | E138: M | F138: 42027 | G138: 30254 | H138: 982064015 | I138: INGENIERIA | J138: INGENIERIA | K138: TECNICO DE SERVICIOS GENERALES | L138: Indefinido | M138: Ordinaria ART 22 | N138: Sindicato 2 | O138: mensual | P138: 42.5
A139: 21.348.035-9 | B139: Activo | C139: Venegas Zuñiga Danae Vaitiare | D139: F-3oct25 | E139: F | F139: 45950 | G139: 37823 | H139: 938741771 | I139: MEMO | J139: PALAFITO | K139: PLAQUECERO(A)/COCINERO(A) | L139: Plazo fijo | M139: Ordinaria ART 22 | N139: Extensión de Beneficio Sindicato 2 | O139: mensual | P139: 42.5 | Q139: 46006
A140: 10.354.706-7 | B140: Activo | C140: Nuñez Araya Roberto Raul | D140: F1 | E140: M | F140: 43887 | G140: 24521 | H140: 976538711 | I140: INGENIERIA | J140: INGENIERIA | K140: TECNICO DE SERVICIOS GENERALES | L140: Indefinido | M140: Ordinaria ART 22 | N140: Sindicato 1 | O140: mensual | P140: 42.5
A141: 24.697.078-5 | B141: Activo | C141: Suarez Rodrigo | D141: F1 | E141: M | F141: 43080 | G141: 28744 | H141: 981937637 | I141: INGENIERIA | J141: INGENIERIA | K141: TECNICO DE SERVICIOS GENERALES | L141: Indefinido | M141: Ordinaria ART 22 | N141: Sindicato 1 | O141: mensual | P141: 42.5
A142: 7.739.041-3 | B142: Activo | C142: Suazo Mardones Hermogenes Leoncio | D142: F1 | E142: M | F142: 41533 | G142: 20384 | H142: 999980971 | I142: INGENIERIA | J142: INGENIERIA | K142: TECNICO DE SERVICIOS GENERALES | L142: Indefinido | M142: Ordinaria ART 22 | N142: Sindicato 2 | O142: mensual | P142: 42.5
A143: 19.404.144-6 | B143: Activo | C143: Araya Parraguez Valentina Ignacia | D143: F1 | E143: F | F143: 45262 | G143: 35324 | H143: 982189310 | I143: ROOMS | J143: HSKP - OTHERS | K143: SUPERVISORA DE AREAS PUBLICAS | L143: Indefinido | M143: Ordinaria ART 22 | N143: Sindicato 2 | O143: mensual | P143: 42.5
A144: 21.460.506-6 | B144: Activo | C144: Valdés Eyzaguirre Jael Constanza | D144: F-3oct25 | E144: F | F144: 45949 | G144: 37964 | H144: 934082343 | I144: ROOMS | J144: HSKP - OTHERS | K144: Supervisor de Housekeeping | L144: Plazo fijo | M144: Ordinaria ART 22 | N144: Extensión de Beneficio Sindicato 2 | O144: mensual | P144: 42.5 | Q144: 46008
A145: 19.670.549-k | B145: Activo | C145: Kuscevic Picand Marie Arianne | D145: F1 | E145: F | F145: 44515 | G145: 35586 | H145: 982831340 | I145: VENTAS Y MARKETING | J145: VENTAS | K145: AGENTE DE RESERVAS | L145: Indefinido | M145: Ordinaria ART 22 | N145: Sindicato 2 | O145: mensual | P145: 42.5
A146: 17.860.453-8 | B146: Activo | C146: Parra Gallardo Gabriela Ester | D146: F1 | E146: F | F146: 45299 | G146: 33525 | H146: 988653727 | I146: VENTAS Y MARKETING | J146: VENTAS | K146: AGENTE DE RESERVAS | L146: Indefinido | M146: Ordinaria ART 22 | N146: Sindicato 2 | O146: mensual | P146: 42.5
A147: 19.783.179-0 | B147: Activo | C147: Tellez Gonzalez Constanza Belen | D147: F1 | E147: F | F147: 44625 | G147: 35701 | H147: 944984603 | I147: VENTAS Y MARKETING | J147: VENTAS | K147: AGENTE DE RESERVAS | L147: Indefinido | M147: Ordinaria ART 22 | N147: Sindicato 2 | O147: mensual | P147: 42.5
A148: 16.662.894-6 | B148: Activo | C148: Marin Calderon Diego Alejandro | D148: F1 | E148: M | F148: 45526 | G148: 32139 | H148: 949068480 | I148: F&B | J148: COCINA | K148: SUPERVISOR DE COCINA | L148: Indefinido | M148: Ordinaria ART 22 | N148: Sindicato 2 | O148: mensual | P148: 42.5
A149: 13.351.108-3 | B149: Activo | C149: Garcia Gonzalez Arnaldo Elias | D149: F1 | E149: M | F149: 38539 | G149: 28565 | H149: 992299418 | I149: INGENIERIA | J149: INGENIERIA | K149: TECNICO DE SERVICIOS GENERALES | L149: Indefinido | M149: Ordinaria ART 22 | N149: Sindicato 2 | O149: mensual | P149: 42.5
A150: 18.938.881-0 | B150: Activo | C150: Jorquera Saavedra Dara Abigail | D150: F-3oct25 | E150: F | F150: 45949 | G150: 34611 | H150: 957065548 | I150: ROOMS | J150: HSKP - OTHERS | K150: Supervisor de Housekeeping | L150: Plazo fijo | M150: Ordinaria ART 22 | N150: Extensión de Beneficio Sindicato 2 | O150: mensual | P150: 42.5 | Q150: 46008
A151: 18.854.285-9 | B151: Activo | C151: Hidalgo Palma Rodrigo Antonio | D151: F1 | E151: M | F151: 45600 | G151: 34765 | H151: 981253621 | I151: ADMINISTRACION Y GERENCIA | J151: CONTRALORIA | K151: AUDITOR DE INGRESOS | L151: Indefinido | M151: Ordinaria ART 22 | N151: Extensión de Beneficio Sindicato 1 | O151: mensual | P151: 42.5
A152: 17.546.677-0 | B152: Activo | C152: Orellana Ruz Jilian Mauricio | D152: F1 | E152: M | F152: 45293 | G152: 32933 | H152: 940498080 | I152: MINOR | J152: GIMNASIO | K152: SUPERVISOR(A) GIMNASIO | L152: Indefinido | M152: Ordinaria ART 22 | N152: Sindicato 1 | O152: mensual | P152: 42.5
A153: 16.627.979-8 | B153: Activo | C153: Letelier Osorio Ismael Ambrosio | D153: F1 | E153: M | F153: 45691 | G153: 32085 | H153: 997931322 | I153: F&B | J153: STEWARD | K153: CHIEF STEWARD | L153: Indefinido | M153: Ordinaria ART 22 | N153: Sindicato 1 | O153: mensual | P153: 42.5
A154: 19.409.032-3 | B154: Activo | C154: Perez Arjona Matias Ignacio | D154: F1 | E154: M | F154: 45370 | G154: 35238 | H154: 965516087 | I154: VENTAS Y MARKETING | J154: DIPLOMATS | K154: Ejecutivo/a Diplomats | L154: Indefinido | M154: Ordinaria ART 22 | N154: Extensión de Beneficio Sindicato 2 | O154: mensual | P154: 42.5
...

Sheet NOMINA OCTUBRE
A1: PEGAR REPORTE " DAILY REPORTE DE BUK " DEL MES ANTERIOR A REPORTAR
A2: MOVER LA COLUMNA DE NUMERO DE DOCUMENTO AL INICIO
A3: ELIMINAR COLUMNA SUELDO BASE
A4: ELIMINAR COLUMNA Haberes No Imponibles - Movilización
A5: ELIMINAR COLUMNA CENTRO COSTOS Y ADICIONALES
A7: Asociado - Número de Documento | B7: Asociado - Estado | C7: Asociado - Nombre Completo | D7: Asociado - Código de Ficha | E7: Asociado - Sexo | F7: Trabajo - Fecha Ingreso Compañía | G7: Asociado - Fecha de Nacimiento | H7: Asociado - Teléfono Particular | I7: Trabajo - Nombre Área | J7: Trabajo - Nombre Sub-área Asignada(o) | K7: Trabajo - Cargo | L7: Trabajo - Tipo de Contrato | M7: Trabajo - Tipo de Jornada | N7: Trabajo - Sindicato | O7: Trabajo - Jornada Laboral | P7: Trabajo - Horas Semanales | Q7: Trabajo - Fecha Vencimiento Contrato
A8: 25.724.970-0 | B8: Inactivo | C8: Araujo Moya Naibel Del Valle | D8: F-1jul25 | E8: F | F8: 45839 | G8: 31847 | H8: 971772773 | I8: MEMO | J8: PALAFITO | K8: CHEF ENCARGADO DE PALAFITO | L8: Plazo fijo | M8: Ordinaria ART 22 | N8: Extensión de Beneficio Sindicato 1 | O8: mensual | P8: 42.5 | Q8: 45932
A9: 14.171.763-4 | B9: Activo | C9: Román Ferreira Susana Inés | D9: F-1sep25 | E9: F | F9: 45902 | G9: 29445 | H9: 950516210 | I9: F&B | J9: STEWARD | K9: PLAQUECERO | L9: Plazo fijo | M9: Ordinaria ART 22 | N9: Extensión de Beneficio Sindicato 2 | O9: mensual | P9: 42.5 | Q9: 46008
A10: 16.369.570-7 | B10: Activo | C10: Fuentes Castillo Macarena Alejandra | D10: F1 | E10: F | F10: 45873 | G10: 32003 | H10: 994060922 | I10: F&B | J10: OFICINA DE BANQUETES | K10: COORDINADOR(A) DE BANQUETES | L10: Plazo fijo | M10: Ordinaria ART 22 | N10: Extensión de Beneficio Sindicato 1 | O10: mensual | P10: 42.5 | Q10: 45964
A11: 18.629.669-9 | B11: Inactivo | C11: Hernández Jorquera Pablo Andrés | D11: F-1ago25 | E11: M | F11: 45873 | G11: 34492 | H11: 995130891 | I11: F&B | J11: STEWARD | K11: PLAQUECERO | L11: Plazo fijo | M11: Ordinaria ART 22 | N11: Extensión de Beneficio Sindicato 2 | O11: mensual | P11: 42.5 | Q11: 45947
A12: 23.816.541-5 | B12: Activo | C12: Pecovnik Cortes Igor | D12: F1 | E12: M | F12: 42911 | G12: 26528 | H12: 999368991 | I12: ROOMS | J12: GROOMS | K12: Grooms/Portero/Valet | L12: Indefinido | M12: Ordinaria ART 22 | N12: Sindicato 1 | O12: mensual | P12: 42.5
A13: 21.042.313-3 | B13: Activo | C13: Gonzalez Muñoz Diego Andres | D13: F-2sep25 | E13: M | F13: 45909 | G13: 37420 | H13: 930232989 | I13: F&B | J13: COCINA | K13: COMMIS | L13: Plazo fijo | M13: Ordinaria ART 22 | N13: Extensión de Beneficio Sindicato 1 | O13: mensual | P13: 42.5 | Q13: 46001
A14: 19.894.223-5 | B14: Activo | C14: Faundez Vallejos Ailin Cricel | D14: F1 | E14: F | F14: 45740 | G14: 35733 | H14: 966647464 | I14: ADMINISTRACION Y GERENCIA | J14: SEGURIDAD | K14: GUARDIA | L14: Indefinido | M14: Ordinaria ART 22 | N14: Sindicato 1 | O14: mensual | P14: 44
A15: 21.498.229-3 | B15: Inactivo | C15: Muñoz Iturra Ignacio Antonio | D15: F-1ago25 | E15: M | F15: 45876 | G15: 38018 | H15: 627092500 | I15: F&B | J15: COCINA | K15: COMMIS | L15: Plazo fijo | M15: Ordinaria ART 22 | N15: Extensión de Beneficio Sindicato 1 | O15: mensual | P15: 42.5 | Q15: 45950
A16: 21.559.331-2 | B16: Inactivo | C16: Pinto Herrera Maria Cristina | D16: F-1ago25 | E16: F | F16: 45876 | G16: 38101 | H16: 963867755 | I16: F&B | J16: COCINA | K16: COMMIS | L16: Plazo fijo | M16: Ordinaria ART 22 | N16: Extensión de Beneficio Sindicato 1 | O16: mensual | P16: 42.5 | Q16: 45950
A17: 19.429.624-k | B17: Activo | C17: Pons Valenzuela Fernanda Edith | D17: F1 | E17: F | F17: 45733 | G17: 35314 | H17: 957168583 | I17: F&B | J17: COCINA | K17: COMMIS | L17: Indefinido | M17: Ordinaria ART 22 | N17: Sindicato 1 | O17: mensual | P17: 42.5
A18: 25.399.125-9 | B18: Activo | C18: Seljak Piña Franz Isidro | D18: F1 | E18: F | F18: 45698 | G18: 34083 | H18: 958147239 | I18: F&B | J18: COCINA | K18: CHEF DE PARTIE | L18: Indefinido | M18: Ordinaria ART 22 | N18: Sindicato 1 | O18: mensual | P18: 42.5
A19: 19.837.527-6 | B19: Activo | C19: Troncoso Enriquez Luis David | D19: F1 | E19: M | F19: 45873 | G19: 35732 | H19: 965198972 | I19: ROOMS | J19: GUEST SERVICES AGENT | K19: GUEST SERVICE AGENT | L19: Indefinido | M19: Ordinaria ART 22 | N19: Extensión de Beneficio Sindicato 2 | O19: mensual | P19: 42.5
A20: 18.637.768-0 | B20: Inactivo | C20: Bastías González María Jesús | D20: F2jul25 | E20: F | F20: 45845 | G20: 34178 | H20: 974960934 | I20: F&B | J20: COCINA | K20: COMMIS | L20: Plazo fijo | M20: Ordinaria ART 22 | N20: Extensión de Beneficio Sindicato 1 | O20: mensual | P20: 42.5 | Q20: 45936
A21: 10.234.877-k | B21: Activo | C21: Salas Villaceca David Antonio | D21: F1 | E21: M | F21: 38153 | G21: 23601 | H21: 988189560 | I21: ADMINISTRACION Y GERENCIA | J21: CONTRALORIA | K21: CAJERO CENTRAL/COBRADOR | L21: Indefinido | M21: Exenta ART 22 | N21: Extensión de Beneficio Sindicato 1 | O21: mensual | P21: 42.5
A22: 26.610.495-2 | B22: Activo | C22: Pierre - Esaie | D22: F-1jul25 | E22: M | F22: 45842 | G22: 34217 | H22: 968759462 | I22: F&B | J22: STEWARD | K22: PLAQUECERO | L22: Plazo fijo | M22: Ordinaria ART 22 | N22: Extensión de Beneficio Sindicato 1 | O22: mensual | P22: 42.5 | Q22: 45986
A23: 21.484.420-6 | B23: Inactivo | C23: Huechantes Obando Joshua Del Piero | D23: F-3ago25 | E23: M | F23: 45892 | G23: 37997 | H23: 941175921 | I23: F&B | J23: LOBBY BAR | K23: BARTENDER | L23: Plazo fijo | M23: Ordinaria ART 22 | N23: Extensión de Beneficio Sindicato 1 | O23: mensual | P23: 42.5 | Q23: 45946
A24: 17.924.524-8 | B24: Activo | C24: Marinao Cid Gabriel Isaías | D24: F1 | E24: M | F24: 45810 | G24: 33394 | H24: 926220231 | I24: ADMINISTRACION Y GERENCIA | J24: SEGURIDAD | K24: GUARDIA | L24: Indefinido | M24: Ordinaria ART 22 | N24: Sindicato 1 | O24: mensual | P24: 44
A25: 26.854.920-k | B25: Inactivo | C25: Romelus - Ralph | D25: F-2jul25 | E25: M | F25: 45849 | G25: 23475 | H25: 933593190 | I25: F&B | J25: STEWARD | K25: PLAQUECERO | L25: Plazo fijo | M25: Ordinaria ART 22 | N25: Extensión de Beneficio Sindicato 1 | O25: mensual | P25: 42.5 | Q25: 45938
A26: 21.286.136-7 | B26: Activo | C26: Fieldhouse Reyes Alonso Emilio | D26: F1 | E26: M | F26: 45864 | G26: 37736 | H26: 965773140 | I26: ROOMS | J26: GUEST SERVICES AGENT | K26: GUEST SERVICE AGENT | L26: Indefinido | M26: Ordinaria ART 22 | N26: Sindicato 1 | O26: mensual | P26: 42.5
A27: 26.187.200-5 | B27: Inactivo | C27: Cobo Serna Paula Andrea | D27: F-2sep25 | E27: F | F27: 45908 | G27: 28309 | H27: 979137813 | I27: ROOMS | J27: AMA DE LLAVES | K27: MUCAMA (O) /ASEADOR (A) /LENCERA (O) | L27: Plazo fijo | M27: Ordinaria ART 22 | N27: Extensión de Beneficio Sindicato 2 | O27: mensual | P27: 42.5 | Q27: 45949
A28: 24.753.417-2 | B28: Activo | C28: Velazquez Maria Eugenia | D28: F-3sep25 | E28: F | F28: 45915 | G28: 32347 | H28: 986908175 | I28: MEMO | J28: PALAFITO | K28: AYUDANTE DE COCINA / PLAQUECERO | L28: Plazo fijo | M28: Ordinaria ART 22 | N28: Extensión de Beneficio Sindicato 1 | O28: mensual | P28: 42.5 | Q28: 45973
A29: 20.328.286-9 | B29: Inactivo | C29: Lopez Soto Benjamin Alejandro | D29: F-1sep25 | E29: M | F29: 45901 | G29: 36432 | H29: 948489580 | I29: F&B | J29: STEWARD | K29: PLAQUECERO | L29: Plazo fijo | M29: Ordinaria ART 22 | N29: Extensión de Beneficio Sindicato 1 | O29: mensual | P29: 42.5 | Q29: 45949
A30: 25.519.267-1 | B30: Inactivo | C30: Henry - Bertha | D30: F-2jul25 | E30: F | F30: 45849 | G30: 33365 | H30: 932969731 | I30: F&B | J30: STEWARD | K30: PLAQUECERO | L30: Plazo fijo | M30: Ordinaria ART 22 | N30: Extensión de Beneficio Sindicato 1 | O30: mensual | P30: 42.5 | Q30: 45938
A31: 15.381.940-8 | B31: Activo | C31: Mora Gutierrez Rodrigo Alejandro | D31: F1 | E31: M | F31: 45854 | G31: 30236 | H31: 973379381 | I31: F&B | J31: STEWARD | K31: PLAQUECERO | L31: Indefinido | M31: Ordinaria ART 22 | N31: Sindicato 1 | O31: mensual | P31: 42.5
A32: 9.608.528-1 | B32: Activo | C32: Sepulveda Veloso Javier Antonio | D32: F1 | E32: M | F32: 45356 | G32: 23263 | H32: 997339466 | I32: ADMINISTRACION Y GERENCIA | J32: SEGURIDAD | K32: GUARDIA | L32: Indefinido | M32: Ordinaria ART 22 | N32: Sindicato 1 | O32: mensual | P32: 44
A33: 20.464.927-8 | B33: Inactivo | C33: Rojas Avalos Diego Alonso | D33: F-4jul25 | E33: M | F33: 45861 | G33: 36580 | H33: 965753637 | I33: F&B | J33: CID | K33: GARZON/CAJERO OUTLETS | L33: Plazo fijo | M33: Ordinaria ART 22 | N33: Extensión de Beneficio Sindicato 1 | O33: mensual | P33: 42.5 | Q33: 45945
A34: 21.229.689-9 | B34: Inactivo | C34: Flores Mora Bastián Salomón | D34: F-4ago25 | E34: M | F34: 45887 | G34: 37658 | H34: 947476835 | I34: ROOMS | J34: GROOMS | K34: PORTERO/GROOM | L34: Plazo fijo | M34: Ordinaria ART 22 | N34: Extensión de Beneficio Sindicato 1 | O34: mensual | P34: 42.5 | Q34: 45945
A35: 21.348.035-9 | B35: Inactivo | C35: Venegas Zuñiga Danae Vaitiare | D35: F-1ago25 | E35: F | F35: 45873 | G35: 37823 | H35: 938741771 | I35: MEMO | J35: PALAFITO | K35: PLAQUECERO(A)/COCINERO(A) | L35: Plazo fijo | M35: Ordinaria ART 22 | N35: Extensión de Beneficio Sindicato 2 | O35: mensual | P35: 42.5 | Q35: 45947
A36: 15.663.854-4 | B36: Inactivo | C36: Díaz Pérez Angelina Karina | D36: F-2sep25 | E36: F | F36: 45908 | G36: 30601 | H36: 958084027 | I36: ROOMS | J36: AMA DE LLAVES | K36: MUCAMA (O) /ASEADOR (A) /LENCERA (O) | L36: Plazo fijo | M36: Ordinaria ART 22 | N36: Extensión de Beneficio Sindicato 2 | O36: mensual | P36: 42.5 | Q36: 45936
A37: 21.010.433-k | B37: Inactivo | C37: Valenzuela Morales Catalina Andrea | D37: F-2sep25 | E37: F | F37: 45913 | G37: 37385 | H37: 977292815 | I37: ROOMS | J37: GUEST SERVICES AGENT | K37: GUEST SERVICE AGENT | L37: Plazo fijo | M37: Parcial ART 40 BIS | O37: diaria | P37: 20 | Q37: 45935
A38: 20.986.847-4 | B38: Inactivo | C38: Ponce Vega Matias Andres | D38: F-4jul25 | E38: M | F38: 45868 | G38: 37332 | H38: 930544509 | I38: F&B | J38: CID | K38: GARZON/CAJERO OUTLETS | L38: Plazo fijo | M38: Ordinaria ART 22 | N38: Extensión de Beneficio Sindicato 1 | O38: mensual | P38: 42.5 | Q38: 45947
A39: 24.083.390-5 | B39: Inactivo | C39: Padilla Arancibia Cinthia Marcela | D39: F-2sep25 | E39: F | F39: 45908 | G39: 30815 | H39: 940013897 | I39: MEMO | J39: PALAFITO | K39: COMMIS | L39: Plazo fijo | M39: Ordinaria ART 22 | N39: Extensión de Beneficio Sindicato 2 | O39: mensual | P39: 42.5 | Q39: 45950
A40: 28.643.071-6 | B40: Inactivo | C40: Garrido Colmenares Carlos Henrrique | D40: F-4jul25 | E40: M | F40: 45863 | G40: 29786 | H40: 932388896 | I40: ROOMS | J40: PUBLIC AREAS | K40: ASEADOR (A) /OPERARIO DE LAVANDERIA | L40: Plazo fijo | M40: Ordinaria ART 22 | N40: Extensión de Beneficio Sindicato 2 | O40: mensual | P40: 42.5 | Q40: 45945
A41: 26.008.888-2 | B41: Activo | C41: Ambroise - Faniel | D41: F-1sep25 | E41: M | F41: 45907 | G41: 30407 | H41: 936527566 | I41: F&B | J41: STEWARD | K41: PLAQUECERO | L41: Plazo fijo | M41: Ordinaria ART 22 | N41: Extensión de Beneficio Sindicato 1 | O41: mensual | P41: 42.5 | Q41: 46008
A42: 12.679.480-0 | B42: Activo | C42: Rebeco Villablanca Freddy Giovanni | D42: F1 | E42: M | F42: 45873 | G42: 27301 | H42: 959430152 | I42: ADMINISTRACION Y GERENCIA | J42: SEGURIDAD | K42: GUARDIA | L42: Indefinido | M42: Ordinaria ART 22 | N42: Extensión de Beneficio Sindicato 1 | O42: mensual | P42: 44
A43: 11.666.268-k | B43: Activo | C43: Zambrano Mandiola Bernarda Julia | D43: F1 | E43: F | F43: 45821 | G43: 25728 | H43: 939582128 | I43: ROOMS | J43: AMA DE LLAVES | K43: MUCAMA (O) /ASEADOR (A) /LENCERA (O) | L43: Indefinido | M43: Ordinaria ART 22 | N43: Sindicato 2 | O43: mensual | P43: 42.5
A44: 26.432.526-9 | B44: Activo | C44: Shephard Matos Francia Elizabeth | D44: F1 | E44: F | F44: 45815 | G44: 29055 | H44: 950352960 | I44: ROOMS | J44: AMA DE LLAVES | K44: MUCAMA (O) /ASEADOR (A) /LENCERA (O) | L44: Indefinido | M44: Ordinaria ART 22 | N44: Sindicato 2 | O44: mensual | P44: 42.5
A45: 20.673.002-1 | B45: Activo | C45: Roco Aguirre Enzo Valentino | D45: F1 | E45: M | F45: 45642 | G45: 36998 | H45: 922004346 | I45: ROOMS | J45: GUEST SERVICES AGENT | K45: GUEST SERVICE AGENT | L45: Indefinido | M45: Ordinaria ART 22 | N45: Sindicato 1 | O45: mensual | P45: 42.5
A46: 26.608.812-4 | B46: Activo | C46: Pascal - Josie | D46: F1 | E46: F | F46: 45815 | G46: 31139 | H46: 932922562 | I46: ROOMS | J46: AMA DE LLAVES | K46: MUCAMA (O) /ASEADOR (A) /LENCERA (O) | L46: Indefinido | M46: Ordinaria ART 22 | N46: Sindicato 2 | O46: mensual | P46: 42.5
A47: 12.876.804-1 | B47: Activo | C47: Córdova Pismante María Silvana | D47: F1 | E47: F | F47: 45815 | G47: 27591 | H47: 961688334 | I47: ROOMS | J47: HSKP - OTHERS | K47: Supervisor de Housekeeping | L47: Indefinido | M47: Ordinaria ART 22 | N47: Sindicato 1 | O47: mensual | P47: 42.5
A48: 20.049.364-8 | B48: Activo | C48: Cortés Romero Ignacio Javier | D48: F1 | E48: M | F48: 45873 | G48: 36260 | H48: 986115473 | I48: INGENIERIA | J48: INGENIERIA | K48: KEN FIX IT | L48: Indefinido | M48: Ordinaria ART 22 | N48: Extensión de Beneficio Sindicato 2 | O48: mensual | P48: 42.5
A49: 19.634.304-0 | B49: Activo | C49: Saavedra Rivas Víctor Ariel | D49: F1 | E49: M | F49: 45873 | G49: 35570 | H49: 933460928 | I49: INGENIERIA | J49: INGENIERIA | K49: KEN FIX IT | L49: Indefinido | M49: Ordinaria ART 22 | N49: Extensión de Beneficio Sindicato 2 | O49: mensual | P49: 42.5
A50: 26.379.552-0 | B50: Inactivo | C50: Martinez Jimenez Oswaldo Euclides | D50: F-1ago25 | E50: M | F50: 45873 | G50: 28727 | H50: 962663325 | I50: F&B | J50: STEWARD | K50: PLAQUECERO | L50: Plazo fijo | M50: Ordinaria ART 22 | N50: Extensión de Beneficio Sindicato 1 | O50: mensual | P50: 42.5 | Q50: 45946
A51: 20.904.996-1 | B51: Inactivo | C51: Arce Contreras Krishna Millaray | D51: F-4jul25 | E51: F | F51: 45868 | G51: 37152 | H51: 955110254 | I51: F&B | J51: CID | K51: GARZON/CAJERO OUTLETS | L51: Plazo fijo | M51: Ordinaria ART 22 | N51: Extensión de Beneficio Sindicato 1 | O51: mensual | P51: 42.5 | Q51: 45936
A52: 28.689.407-0 | B52: Activo | C52: Montaña Sequera Jose Gregorio | D52: F-2jun25 | E52: M | F52: 45820 | G52: 23905 | H52: 947077425 | I52: ROOMS | J52: PUBLIC AREAS | K52: ASEADOR (A) /OPERARIO DE LAVANDERIA | L52: Plazo fijo | M52: Ordinaria ART 22 | N52: Extensión de Beneficio Sindicato 2 | O52: mensual | P52: 42.5 | Q52: 45973
A53: 21.014.986-4 | B53: Inactivo | C53: Medina Santana Matías Andrés | D53: F-1ago25 | E53: M | F53: 45873 | G53: 37395 | H53: 977056092 | I53: F&B | J53: COCINA | K53: COMMIS | L53: Plazo fijo | M53: Ordinaria ART 22 | N53: Extensión de Beneficio Sindicato 1 | O53: mensual | P53: 42.5 | Q53: 45946
A54: 17.317.967-7 | B54: Activo | C54: Maldonado Castro Pablo Andrés | D54: F1 | E54: M | F54: 45873 | G54: 33033 | H54: 932683071 | I54: INGENIERIA | J54: INGENIERIA | K54: ENGINEER II | L54: Indefinido | M54: Ordinaria ART 22 | N54: Extensión de Beneficio Sindicato 1 | O54: mensual | P54: 42.5
A55: 18.307.898-4 | B55: Inactivo | C55: Barros Godoy Luis Paulo | D55: F-1ago25 | E55: M | F55: 45873 | G55: 32883 | H55: 954591208 | I55: INGENIERIA | J55: INGENIERIA | K55: ENGINEER II | L55: Plazo fijo | M55: Ordinaria ART 22 | N55: Extensión de Beneficio Sindicato 1 | O55: mensual | P55: 42.5 | Q55: 45950
A56: 17.105.874-0 | B56: Activo | C56: Soñan Marifil Mariana Angelica | D56: F1 | E56: F | F56: 45810 | G56: 32662 | H56: 951895642 | I56: F&B | J56: COCINA | K56: CHEF DE PARTIE | L56: Indefinido | M56: Ordinaria ART 22 | N56: Sindicato 1 | O56: mensual | P56: 42.5
A57: 16.373.482-6 | B57: Activo | C57: Fernández Gómez José Luis | D57: F1 | E57: M | F57: 45810 | G57: 31549 | H57: 967268112 | I57: ADMINISTRACION Y GERENCIA | J57: STORE COST CONTROL | K57: ENCARGADO DE BODEGA | L57: Indefinido | M57: Ordinaria ART 22 | N57: Sindicato 1 | O57: mensual | P57: 42.5
A58: 13.255.671-7 | B58: Activo | C58: Gómez Zenteno Rafael Andrés | D58: F-1ago25 | E58: M | F58: 45873 | G58: 28259 | H58: 951557885 | I58: VENTAS Y MARKETING | J58: DIPLOMATS | K58: Ejecutivo/a Diplomats | L58: Plazo fijo | M58: Ordinaria ART 22 | N58: Extensión de Beneficio Sindicato 2 | O58: mensual | P58: 42.5 | Q58: 46026
A59: 14.131.634-6 | B59: Activo | C59: Menchaca Fernández María Constanza | D59: F1 | E59: F | F59: 45803 | G59: 29666 | H59: 994358167 | I59: VENTAS Y MARKETING | J59: VENTAS | K59: EJECUTIVA DE VENTAS DE NUEVOS NEGOCIOS | L59: Indefinido | M59: Exenta ART 22 | N59: Extensión de Beneficio Sindicato 2 | O59: mensual | P59: 44
A60: 20.108.477-6 | B60: Activo | C60: Moreno Laso Vicente Daniel | D60: F1 | E60: M | F60: 45810 | G60: 36248 | H60: 942775139 | I60: ADMINISTRACION Y GERENCIA | J60: CONTRALORIA | K60: Auxiliar de Créditos | L60: Indefinido | M60: Ordinaria ART 22 | N60: Extensión de Beneficio Sindicato 2 | O60: mensual | P60: 42.5
A61: 20.761.204-9 | B61: Activo | C61: Parra Quezada Giulliana Stephani | D61: F1 | E61: F | F61: 45810 | G61: 37023 | H61: 939039706 | I61: ADMINISTRACION Y GERENCIA | J61: CONTRALORIA | K61: Auxiliar de Créditos | L61: Indefinido | M61: Ordinaria ART 22 | N61: Extensión de Beneficio Sindicato 1 | O61: mensual | P61: 42.5
A62: 10.807.412-4 | B62: Activo | C62: Sáez Barrios Jean Eric | D62: F1 | E62: M | F62: 45810 | G62: 28931 | H62: 968141966 | I62: VENTAS Y MARKETING | J62: VENTAS | K62: Ejecutivo de Cuentas Tour & Travel | L62: Indefinido | M62: Exenta ART 22 | N62: Extensión de Beneficio Sindicato 1 | O62: mensual | P62: 44
A63: 27.917.972-2 | B63: Activo | C63: Fernandez Mambuscay Julian Estiben | D63: F1 | E63: M | F63: 44972 | G63: 37092 | H63: 993010961 | I63: F&B | J63: STEWARD | K63: SUPERVISOR STEWARD | L63: Indefinido | M63: Ordinaria ART 22 | N63: Sindicato 1 | O63: mensual | P63: 42.5
A64: 26.409.239-6 | B64: Activo | C64: Anzola Villalon Juan Carlos | D64: F1 | E64: M | F64: 43608 | G64: 27715 | H64: 994905005 | I64: F&B | J64: STEWARD | K64: SUPERVISOR STEWARD | L64: Indefinido | M64: Ordinaria ART 22 | N64: Sindicato 1 | O64: mensual | P64: 42.5
A65: 28.184.786-4 | B65: Activo | C65: Feltran Loubens | D65: F1 | E65: M | F65: 45298 | G65: 34281 | H65: 936263836 | I65: F&B | J65: STEWARD | K65: SUPERVISOR STEWARD | L65: Indefinido | M65: Ordinaria ART 22 | N65: Sindicato 1 | O65: mensual | P65: 42.5
A66: 21.355.332-1 | B66: Inactivo | C66: Monroy Herrera Edelein Jeannette | D66: F-2sep25 | E66: F | F66: 45912 | G66: 37830 | H66: 944708189 | I66: ROOMS | J66: GUEST SERVICES AGENT | K66: GUEST SERVICE AGENT | L66: Plazo fijo | M66: Parcial ART 40 BIS | O66: diaria | P66: 20 | Q66: 45935
A67: 19.664.249-8 | B67: Inactivo | C67: Martinez Beltran Victor Manuel | D67: F-1sep25 | E67: M | F67: 45904 | G67: 35915 | H67: 961704610 | I67: ROOMS | J67: GUEST SERVICES AGENT | K67: GUEST SERVICE AGENT | L67: Plazo fijo | M67: Ordinaria ART 22 | N67: Extensión de Beneficio Sindicato 2 | O67: mensual | P67: 42.5 | Q67: 45931
A68: 21.774.085-1 | B68: Inactivo | C68: Jamed Cabezas Amanda Francisca | D68: F-1sep25 | E68: F | F68: 45904 | G68: 38396 | H68: 971085903 | I68: ROOMS | J68: GUEST SERVICES AGENT | K68: GUEST SERVICE AGENT | L68: Plazo fijo | M68: Ordinaria ART 22 | N68: Extensión de Beneficio Sindicato 2 | O68: mensual | P68: 42.5 | Q68: 45931
A69: 26.342.208-2 | B69: Activo | C69: Meza Guzman Christian Modesto | D69: F-1sep25 | E69: M | F69: 45904 | G69: 31939 | H69: 947017455 | I69: F&B | J69: CID | K69: GARZON/CAJERO OUTLETS | L69: Plazo fijo | M69: Ordinaria ART 22 | N69: Extensión de Beneficio Sindicato 2 | O69: mensual | P69: 42.5 | Q69: 45985
A70: 19.824.335-3 | B70: Inactivo | C70: Mardones Melo Esteban Elias | D70: F-1sep25 | E70: M | F70: 45903 | G70: 36036 | H70: 932964723 | I70: F&B | J70: ROOM SERVICE | K70: GARZON/CAJERO OUTLETS | L70: Plazo fijo | M70: Ordinaria ART 22 | O70: mensual | P70: 42.5 | Q70: 45949
A71: 13.679.411-6 | B71: Activo | C71: Irarrazabal Contreras Sabrina Gisella | D71: F1 | E71: F | F71: 45266 | G71: 28879 | H71: 983037941 | I71: F&B | J71: CID | K71: BARTENDER | L71: Indefinido | M71: Ordinaria ART 22 | N71: Sindicato 1 | O71: mensual | P71: 42.5
A72: 17.217.358-6 | B72: Activo | C72: Borquez Venegas Mario Alejandro | D72: F1 | E72: M | F72: 45278 | G72: 32862 | H72: 56983577085 | I72: F&B | J72: LOBBY BAR | K72: BARTENDER | L72: Indefinido | M72: Ordinaria ART 22 | N72: Sindicato 1 | O72: mensual | P72: 42.5
A73: 19.292.167-8 | B73: Activo | C73: Martinez Pérez Francisca Andrea | D73: F1 | E73: F | F73: 45670 | G73: 35142 | H73: 936559107 | I73: F&B | J73: LOBBY BAR | K73: BARTENDER | L73: Indefinido | M73: Ordinaria ART 22 | N73: Sindicato 1 | O73: mensual | P73: 42.5
A74: 19.736.484-k | B74: Activo | C74: Arevalo Díaz Ignacio Alfonso | D74: F1 | E74: M | F74: 45666 | G74: 35747 | H74: 985013018 | I74: F&B | J74: LOBBY BAR | K74: BARTENDER | L74: Indefinido | M74: Ordinaria ART 22 | N74: Sindicato 1 | O74: mensual | P74: 42.5
A75: 18.097.808-9 | B75: Inactivo | C75: Achurra Castro Christopher Abraham Segundo | D75: F-2ago25 | E75: M | F75: 45880 | G75: 33751 | H75: 979983899 | I75: F&B | J75: BANQUETES SERVICE | K75: SUPERVISOR DE COCINA | L75: Plazo fijo | M75: Ordinaria ART 22 | N75: Extensión de Beneficio Sindicato 2 | O75: mensual | P75: 42.5 | Q75: 45950
A76: 22.458.381-8 | B76: Inactivo | C76: Ibañez Huaman Nalleli Brillid | D76: F-2sep25 | E76: F | F76: 45913 | G76: 39285 | H76: 984553612 | I76: ROOMS | J76: GROOMS | K76: PORTERO/GROOM | L76: Plazo fijo | M76: Ordinaria ART 22 | O76: diaria | P76: 30 | Q76: 45935
A77: 10.730.616-1 | B77: Inactivo | C77: Ortega Rideau Rolando Enrique | D77: F-3ago25 | E77: M | F77: 45887 | G77: 24756 | H77: 982196002 | I77: ROOMS | J77: PUBLIC AREAS | K77: OPERARIO DRY CLEANING | L77: Plazo fijo | M77: Ordinaria ART 22 | N77: Extensión de Beneficio Sindicato 2 | O77: mensual | P77: 42.5 | Q77: 45948
A78: 20.059.173-9 | B78: Activo | C78: Medina Pino Amapola Belen | D78: F1 | E78: F | F78: 45683 | G78: 36273 | H78: 999858027 | I78: F&B | J78: LOBBY BAR | K78: BARTENDER | L78: Indefinido | M78: Ordinaria ART 22 | N78: Sindicato 1 | O78: mensual | P78: 42.5
A79: 20.806.854-7 | B79: Inactivo | C79: Antivilo Aguilar Sebastián Rodrigo | D79: F-2ago25 | E79: M | F79: 45880 | G79: 37105 | H79: 995917174 | I79: F&B | J79: COCINA | K79: COMMIS | L79: Plazo fijo | M79: Ordinaria ART 22 | N79: Extensión de Beneficio Sindicato 2 | O79: mensual | P79: 42.5 | Q79: 45945
A80: 9.091.247-k | B80: Activo | C80: Gonzalez Williams Ignacio Geronimo | D80: F-2ago25 | E80: M | F80: 45880 | G80: 26697 | H80: 973478658 | I80: F&B ADM | J80: F&B ADMINISTRATION | K80: COORDINADOR DE F & B | L80: Plazo fijo | M80: Exenta ART 22 | N80: Extensión de Beneficio Sindicato 2 | O80: mensual | P80: 44 | Q80: 45971
A81: 20.164.622-7 | B81: Activo | C81: Palma Chavez Juan Pablo | D81: F1 | E81: M | F81: 45666 | G81: 36349 | H81: 966368813 | I81: F&B | J81: LOBBY BAR | K81: BARTENDER | L81: Indefinido | M81: Ordinaria ART 22 | N81: Sindicato 1 | O81: mensual | P81: 42.5
A82: 19.220.449-6 | B82: Inactivo | C82: Garay Garay Samantha Gissella | D82: F-3ago25 | E82: F | F82: 45887 | G82: 34980 | H82: 923985932 | I82: ROOMS | J82: AMA DE LLAVES | K82: MUCAMA (O) /ASEADOR (A) /LENCERA (O) | L82: Plazo fijo | M82: Ordinaria ART 22 | N82: Extensión de Beneficio Sindicato 2 | O82: mensual | P82: 42.5 | Q82: 45948
A83: 19.986.412-2 | B83: Activo | C83: Bustos Pradine Francisco Javier | D83: F1 | E83: M | F83: 45335 | G83: 36260 | H83: 987578812 | I83: MEMO | J83: PALAFITO | K83: COMMIS | L83: Indefinido | M83: Ordinaria ART 22 | N83: Sindicato 1 | O83: mensual | P83: 42.5
A84: 21.408.179-2 | B84: Activo | C84: Valdes Muñoz Maiva Ailyn | D84: F1 | E84: F | F84: 45203 | G84: 37904 | H84: 999671185 | I84: F&B | J84: LOBBY BAR | K84: BARTENDER | L84: Indefinido | M84: Ordinaria ART 22 | N84: Sindicato 1 | O84: mensual | P84: 42.5
A85: 21.980.969-7 | B85: Inactivo | C85: Contreras Gallardo Martin Ricardo | D85: F-2sep25 | E85: M | F85: 45913 | G85: 38673 | H85: 942824175 | I85: MEMO | J85: PALAFITO | K85: COMMIS | L85: Plazo fijo | M85: Ordinaria ART 22 | N85: Extensión de Beneficio Sindicato 2 | O85: mensual | P85: 42.5 | Q85: 45948
A86: 19.169.894-0 | B86: Inactivo | C86: Toro Caniuñir Paula Francisca | D86: F-3ago25 | E86: F | F86: 45887 | G86: 34736 | H86: 933783696 | I86: ROOMS | J86: AMA DE LLAVES | K86: MUCAMA (O) /ASEADOR (A) /LENCERA (O) | L86: Plazo fijo | M86: Ordinaria ART 22 | N86: Extensión de Beneficio Sindicato 2 | O86: mensual | P86: 42.5 | Q86: 45948
A87: 21.790.892-2 | B87: Inactivo | C87: Vera Porma Vania Alejandra | D87: F-3ago25 | E87: F | F87: 45887 | G87: 38418 | H87: 934061606 | I87: ROOMS | J87: AMA DE LLAVES | K87: MUCAMA (O) /ASEADOR (A) /LENCERA (O) | L87: Plazo fijo | M87: Ordinaria ART 22 | N87: Extensión de Beneficio Sindicato 2 | O87: mensual | P87: 42.5 | Q87: 45948
A88: 21.687.551-6 | B88: Activo | C88: Riffo Carrera Alejandra Paz | D88: F1 | E88: F | F88: 45228 | G88: 38281 | H88: 984972369 | I88: F&B | J88: LOBBY BAR | K88: BARTENDER | L88: Indefinido | M88: Ordinaria ART 22 | N88: Sindicato 1 | O88: mensual | P88: 42.5
A89: 21.747.982-7 | B89: Activo | C89: Torres Arancibia Ignacio Antonio | D89: F1 | E89: M | F89: 45666 | G89: 38356 | H89: 977332771 | I89: F&B | J89: CID | K89: BARTENDER | L89: Indefinido | M89: Ordinaria ART 22 | N89: Sindicato 1 | O89: mensual | P89: 42.5
A90: 18.522.905-k | B90: Activo | C90: Cabezas Herrera Cristian Ignacio | D90: F1 | E90: M | F90: 45136 | G90: 36034 | H90: 991453127 | I90: F&B | J90: BANQUETES SERVICE | K90: CAPITAN DE BARES | L90: Indefinido | M90: Ordinaria ART 22 | N90: Sindicato 1 | O90: mensual | P90: 42.5
A91: 12.264.591-6 | B91: Inactivo | C91: Salinas Sanchez Paula Andrea | D91: F-3ago25 | E91: F | F91: 45887 | G91: 26511 | H91: 994421787 | I91: ROOMS | J91: HSKP - OTHERS | K91: Supervisor de Housekeeping | L91: Plazo fijo | M91: Ordinaria ART 22 | N91: Extensión de Beneficio Sindicato 1 | O91: mensual | P91: 42.5 | Q91: 45946
A92: 11.395.482-5 | B92: Inactivo | C92: Domínguez Saldaña Carla Verónica | D92: F-3ago25 | E92: F | F92: 45887 | G92: 25202 | H92: 961933719 | I92: ROOMS | J92: PUBLIC AREAS | K92: ASEADOR (A) /OPERARIO DE LAVANDERIA | L92: Plazo fijo | M92: Ordinaria ART 22 | N92: Extensión de Beneficio Sindicato 2 | O92: mensual | P92: 42.5 | Q92: 45948
A93: 19.803.249-2 | B93: Activo | C93: Caballero Francovich Nicole Carolina | D93: F1 | E93: F | F93: 45201 | G93: 35864 | H93: 962753320 | I93: F&B | J93: BANQUETES SERVICE | K93: GARZON/CAJERO OUTLETS | L93: Indefinido | M93: Ordinaria ART 22 | N93: Sindicato 1 | O93: mensual | P93: 42.5
A94: 18.938.881-0 | B94: Inactivo | C94: Jorquera Saavedra Dara Abigail | D94: F-3ago25 | E94: F | F94: 45887 | G94: 34611 | H94: 957065548 | I94: ROOMS | J94: HSKP - OTHERS | K94: Supervisor de Housekeeping | L94: Plazo fijo | M94: Ordinaria ART 22 | N94: Extensión de Beneficio Sindicato 2 | O94: mensual | P94: 42.5 | Q94: 45946
A95: 21.460.506-6 | B95: Inactivo | C95: Valdés Eyzaguirre Jael Constanza | D95: F-3ago25 | E95: F | F95: 45887 | G95: 37964 | H95: 934082343 | I95: ROOMS | J95: HSKP - OTHERS | K95: Supervisor de Housekeeping | L95: Plazo fijo | M95: Ordinaria ART 22 | N95: Extensión de Beneficio Sindicato 2 | O95: mensual | P95: 42.5 | Q95: 45946
A96: 10.647.429-k | B96: Activo | C96: Medel Hernandez Bernarda Del Carmen | D96: F1 | E96: F | F96: 45139 | G96: 25085 | H96: 966866209 | I96: MEMO | J96: PALAFITO | K96: COMMIS | L96: Indefinido | M96: Ordinaria ART 22 | N96: Sindicato 1 | O96: mensual | P96: 42.5
A97: 12.156.808-k | B97: Activo | C97: Castillo Arroyo Maria Del Carmen | D97: F1 | E97: F | F97: 45615 | G97: 24228 | H97: 951955957 | I97: MEMO | J97: PALAFITO | K97: PLAQUECERO(A)/COCINERO(A) | L97: Indefinido | M97: Ordinaria ART 22 | N97: Sindicato 1 | O97: mensual | P97: 42.5
A98: 18.078.928-6 | B98: Activo | C98: Santa Cruz Silva Constanza Deyanira | D98: F1 | E98: F | F98: 45375 | G98: 33644 | H98: 937094777 | I98: MEMO | J98: PALAFITO | K98: COMMIS | L98: Indefinido | M98: Ordinaria ART 22 | N98: Sindicato 1 | O98: mensual | P98: 42.5
A99: 21.136.259-6 | B99: Activo | C99: Segura Salva Marcela Monserratt | D99: F1 | E99: F | F99: 45623 | G99: 37524 | H99: 981587467 | I99: MEMO | J99: PALAFITO | K99: COMMIS | L99: Indefinido | M99: Ordinaria ART 22 | N99: Extensión de Beneficio Sindicato 1 | O99: mensual | P99: 42.5
A100: 19.518.299-k | B100: Activo | C100: Fuentes Alfaro Melissa Belen | D100: F1 | E100: F | F100: 45364 | G100: 35142 | H100: 985027177 | I100: F&B | J100: COCINA | K100: DEMI/CHEF | L100: Indefinido | M100: Ordinaria ART 22 | N100: Sindicato 1 | O100: mensual | P100: 42.5
A101: 26.322.097-8 | B101: Activo | C101: Georges Marie Laure | D101: F1 | E101: F | F101: 45580 | G101: 34296 | H101: 959220479 | I101: MEMO | J101: PALAFITO | K101: PLAQUECERO(A)/COCINERO(A) | L101: Indefinido | M101: Ordinaria ART 22 | N101: Sindicato 1 | O101: mensual | P101: 42.5
...

Sheet REPORTE FINIQUITO DEL MES A REP
A1: PEGAR REPORTE DE FINIQUITOS DEL MES A ENVIAR
A2: ELIMINAR COLUMNA DE SUELDO LIQUIDO
A4: Asociado - Número de Documento | B4: Asociado - Estado | C4: Asociado - Código de Ficha | D4: Asociado - Nombre Completo | E4: Trabajo - Fecha Ingreso Compañía | F4: Trabajo - Fecha Vencimiento Contrato | G4: Trabajo - Tipo de Contrato | H4: Trabajo - Tipo de Jornada | I4: Trabajo - Jornada Laboral | J4: Asociado - Forma de Pago | K4: Asociado - Banco | L4: Asociado - Tipo de Cuenta | M4: Asociado - Número de Cuenta | N4: Trabajo - Fecha Término Trabajo | O4: Trabajo - Razón de Término | P4: Trabajo - Comentario Interno de Término | Q4: Asociado - Fecha Pago de Finiquito | R4: Campos Personalizados de Asociado - Estado Finiquito | S4: Campos Personalizados de Asociado - Forma Pago Finiquito | T4: Campos Personalizados de Asociado - Fecha de Pago
A5: 25.724.970-0 | B5: Inactivo | C5: F-1jul25 | D5: Araujo Moya Naibel Del Valle | E5: 45839 | F5: 45932 | G5: Plazo fijo | H5: Ordinaria ART 22 | I5: mensual | J5: Transferencia Bancaria | K5: Santander | L5: Corriente | M5: 91530775 | N5: 45932 | O5: vencimiento_plazo | Q5: 45940
A6: 14.171.763-4 | B6: Activo | C6: F-1sep25 | D6: Román Ferreira Susana Inés | E6: 45902 | F6: 46008 | G6: Plazo fijo | H6: Ordinaria ART 22 | I6: mensual | J6: Transferencia Bancaria | K6: Falabella | L6: Corriente | M6: 19822231785
A7: 16.369.570-7 | B7: Activo | C7: F1 | D7: Fuentes Castillo Macarena Alejandra | E7: 45873 | F7: 45964 | G7: Plazo fijo | H7: Ordinaria ART 22 | I7: mensual | J7: Transferencia Bancaria | K7: Falabella | L7: Corriente | M7: 19991394482
A8: 18.629.669-9 | B8: Inactivo | C8: F-1ago25 | D8: Hernández Jorquera Pablo Andrés | E8: 45873 | F8: 45947 | G8: Plazo fijo | H8: Ordinaria ART 22 | I8: mensual | J8: Transferencia Bancaria | K8: Banco Estado | L8: Vista | M8: 18629669 | N8: 45947 | O8: vencimiento_plazo | Q8: 45954
A9: 23.816.541-5 | B9: Activo | C9: F1 | D9: Pecovnik Cortes Igor | E9: 42911 | G9: Indefinido | H9: Ordinaria ART 22 | I9: mensual | J9: Transferencia Bancaria | K9: BCI | L9: Corriente | M9: 53090128
A10: 21.042.313-3 | B10: Activo | C10: F-2sep25 | D10: Gonzalez Muñoz Diego Andres | E10: 45909 | F10: 46001 | G10: Plazo fijo | H10: Ordinaria ART 22 | I10: mensual | J10: Transferencia Bancaria | K10: Banco Estado | L10: Vista | M10: 21042313
A11: 19.894.223-5 | B11: Activo | C11: F1 | D11: Faundez Vallejos Ailin Cricel | E11: 45740 | G11: Indefinido | H11: Ordinaria ART 22 | I11: mensual | J11: Transferencia Bancaria | K11: Falabella | L11: Corriente | M11: 19990463037
A12: 21.498.229-3 | B12: Inactivo | C12: F-1ago25 | D12: Muñoz Iturra Ignacio Antonio | E12: 45876 | F12: 45950 | G12: Plazo fijo | H12: Ordinaria ART 22 | I12: mensual | J12: Transferencia Bancaria | K12: Falabella | L12: Corriente | M12: 19812293715 | N12: 45950 | O12: vencimiento_plazo | Q12: 45954
A13: 21.559.331-2 | B13: Inactivo | C13: F-1ago25 | D13: Pinto Herrera Maria Cristina | E13: 45876 | F13: 45950 | G13: Plazo fijo | H13: Ordinaria ART 22 | I13: mensual | J13: Transferencia Bancaria | K13: Banco Estado | L13: Vista | M13: 21559331 | N13: 45950 | O13: vencimiento_plazo | Q13: 45954
A14: 19.429.624-k | B14: Activo | C14: F1 | D14: Pons Valenzuela Fernanda Edith | E14: 45733 | G14: Indefinido | H14: Ordinaria ART 22 | I14: mensual | J14: Transferencia Bancaria | K14: Falabella | L14: Corriente | M14: 12530148336
A15: 25.399.125-9 | B15: Activo | C15: F1 | D15: Seljak Piña Franz Isidro | E15: 45698 | G15: Indefinido | H15: Ordinaria ART 22 | I15: mensual | J15: Transferencia Bancaria | K15: Santander | L15: Corriente | M15: 72107934
A16: 19.837.527-6 | B16: Activo | C16: F1 | D16: Troncoso Enriquez Luis David | E16: 45873 | G16: Indefinido | H16: Ordinaria ART 22 | I16: mensual | J16: Transferencia Bancaria | K16: Santander | L16: Corriente | M16: 82103651 | S16: Electrónico
A17: 18.637.768-0 | B17: Inactivo | C17: F2jul25 | D17: Bastías González María Jesús | E17: 45845 | F17: 45936 | G17: Plazo fijo | H17: Ordinaria ART 22 | I17: mensual | J17: Transferencia Bancaria | K17: Falabella | L17: Corriente | M17: 15841234260 | N17: 45936 | O17: vencimiento_plazo | Q17: 45940
A18: 10.234.877-k | B18: Activo | C18: F1 | D18: Salas Villaceca David Antonio | E18: 38153 | G18: Indefinido | H18: Exenta ART 22 | I18: mensual | J18: Transferencia Bancaria | K18: Itau | L18: Vista | M18: 202221197
A19: 26.610.495-2 | B19: Activo | C19: F-1jul25 | D19: Pierre - Esaie | E19: 45842 | F19: 45986 | G19: Plazo fijo | H19: Ordinaria ART 22 | I19: mensual | J19: Transferencia Bancaria | K19: Falabella | L19: Corriente | M19: 18800154360
A20: 21.484.420-6 | B20: Inactivo | C20: F-3ago25 | D20: Huechantes Obando Joshua Del Piero | E20: 45892 | F20: 45946 | G20: Plazo fijo | H20: Ordinaria ART 22 | I20: mensual | J20: Transferencia Bancaria | K20: Scotiabank | L20: Corriente | M20: 986723342 | N20: 45946 | O20: vencimiento_plazo | Q20: 45947
A21: 17.924.524-8 | B21: Activo | C21: F1 | D21: Marinao Cid Gabriel Isaías | E21: 45810 | G21: Indefinido | H21: Ordinaria ART 22 | I21: mensual | J21: Transferencia Bancaria | K21: Ripley | L21: Corriente | M21: 4014100038
A22: 26.854.920-k | B22: Inactivo | C22: F-2jul25 | D22: Romelus - Ralph | E22: 45849 | F22: 45938 | G22: Plazo fijo | H22: Ordinaria ART 22 | I22: mensual | J22: Transferencia Bancaria | K22: Banco Estado | L22: Vista | M22: 26854920 | N22: 45938 | O22: vencimiento_plazo | Q22: 45940
A23: 21.286.136-7 | B23: Activo | C23: F1 | D23: Fieldhouse Reyes Alonso Emilio | E23: 45864 | G23: Indefinido | H23: Ordinaria ART 22 | I23: mensual | J23: Transferencia Bancaria | K23: Santander | L23: Corriente | M23: 83844507
A24: 26.187.200-5 | B24: Inactivo | C24: F-2sep25 | D24: Cobo Serna Paula Andrea | E24: 45908 | F24: 45949 | G24: Plazo fijo | H24: Ordinaria ART 22 | I24: mensual | J24: Transferencia Bancaria | K24: Banco Estado | L24: Vista | M24: 26187200 | N24: 45949 | O24: vencimiento_plazo | Q24: 45954
A25: 24.753.417-2 | B25: Activo | C25: F-3sep25 | D25: Velazquez Maria Eugenia | E25: 45915 | F25: 45973 | G25: Plazo fijo | H25: Ordinaria ART 22 | I25: mensual | J25: Transferencia Bancaria | K25: Santander | L25: Ahorro | M25: 80626053
A26: 20.328.286-9 | B26: Inactivo | C26: F-1sep25 | D26: Lopez Soto Benjamin Alejandro | E26: 45901 | F26: 45949 | G26: Plazo fijo | H26: Ordinaria ART 22 | I26: mensual | J26: Transferencia Bancaria | K26: Falabella | L26: Vista | M26: 19801473344 | N26: 45938 | O26: renuncia | Q26: 45940
A27: 25.519.267-1 | B27: Inactivo | C27: F-2jul25 | D27: Henry - Bertha | E27: 45849 | F27: 45938 | G27: Plazo fijo | H27: Ordinaria ART 22 | I27: mensual | J27: Transferencia Bancaria | K27: Banco Estado | L27: Vista | M27: 25519267 | N27: 45938 | O27: vencimiento_plazo | Q27: 45940
A28: 15.381.940-8 | B28: Activo | C28: F1 | D28: Mora Gutierrez Rodrigo Alejandro | E28: 45854 | G28: Indefinido | H28: Ordinaria ART 22 | I28: mensual | J28: Transferencia Bancaria | K28: Banco Estado | L28: Vista | M28: 15381940
A29: 9.608.528-1 | B29: Activo | C29: F1 | D29: Sepulveda Veloso Javier Antonio | E29: 45356 | G29: Indefinido | H29: Ordinaria ART 22 | I29: mensual | J29: Transferencia Bancaria | K29: Banco Estado | L29: Vista | M29: 9608528
A30: 20.464.927-8 | B30: Inactivo | C30: F-4jul25 | D30: Rojas Avalos Diego Alonso | E30: 45861 | F30: 45945 | G30: Plazo fijo | H30: Ordinaria ART 22 | I30: mensual | J30: Transferencia Bancaria | K30: Banco Estado | L30: Vista | M30: 20464927 | N30: 45945 | O30: vencimiento_plazo | Q30: 45947
A31: 21.229.689-9 | B31: Inactivo | C31: F-4ago25 | D31: Flores Mora Bastián Salomón | E31: 45887 | F31: 45945 | G31: Plazo fijo | H31: Ordinaria ART 22 | I31: mensual | J31: Transferencia Bancaria | K31: Santander | L31: Vista | M31: 5621229689 | N31: 45945 | O31: vencimiento_plazo | Q31: 45947
A32: 21.348.035-9 | B32: Inactivo | C32: F-1ago25 | D32: Venegas Zuñiga Danae Vaitiare | E32: 45873 | F32: 45947 | G32: Plazo fijo | H32: Ordinaria ART 22 | I32: mensual | J32: Transferencia Bancaria | K32: Banco Estado | L32: Vista | M32: 21348035 | N32: 45947 | O32: vencimiento_plazo | Q32: 45954
A33: 15.663.854-4 | B33: Inactivo | C33: F-2sep25 | D33: Díaz Pérez Angelina Karina | E33: 45908 | F33: 45936 | G33: Plazo fijo | H33: Ordinaria ART 22 | I33: mensual | J33: Transferencia Bancaria | K33: Banco de Chile | L33: Vista | M33: 1311425251 | N33: 45936 | O33: vencimiento_plazo | Q33: 45940
A34: 21.010.433-k | B34: Inactivo | C34: F-2sep25 | D34: Valenzuela Morales Catalina Andrea | E34: 45913 | F34: 45935 | G34: Plazo fijo | H34: Parcial ART 40 BIS | I34: diaria | J34: Transferencia Bancaria | K34: Scotiabank | L34: Corriente | M34: 310001802862 | N34: 45935 | O34: vencimiento_plazo | Q34: 45940
A35: 20.986.847-4 | B35: Inactivo | C35: F-4jul25 | D35: Ponce Vega Matias Andres | E35: 45868 | F35: 45947 | G35: Plazo fijo | H35: Ordinaria ART 22 | I35: mensual | J35: Transferencia Bancaria | K35: Falabella | L35: Corriente | M35: 17240058243 | N35: 45947 | O35: vencimiento_plazo | Q35: 45954
A36: 24.083.390-5 | B36: Inactivo | C36: F-2sep25 | D36: Padilla Arancibia Cinthia Marcela | E36: 45908 | F36: 45950 | G36: Plazo fijo | H36: Ordinaria ART 22 | I36: mensual | J36: Transferencia Bancaria | K36: Banco Estado | L36: Vista | M36: 24083390 | N36: 45950 | O36: vencimiento_plazo | Q36: 45954
A37: 28.643.071-6 | B37: Inactivo | C37: F-4jul25 | D37: Garrido Colmenares Carlos Henrrique | E37: 45863 | F37: 45945 | G37: Plazo fijo | H37: Ordinaria ART 22 | I37: mensual | J37: Cheque | N37: 45945 | O37: vencimiento_plazo | Q37: 45947
A38: 26.008.888-2 | B38: Activo | C38: F-1sep25 | D38: Ambroise - Faniel | E38: 45907 | F38: 46008 | G38: Plazo fijo | H38: Ordinaria ART 22 | I38: mensual | J38: Transferencia Bancaria | K38: Banco Estado | L38: Vista | M38: 26008888
A39: 12.679.480-0 | B39: Activo | C39: F1 | D39: Rebeco Villablanca Freddy Giovanni | E39: 45873 | G39: Indefinido | H39: Ordinaria ART 22 | I39: mensual | J39: Transferencia Bancaria | K39: Banco Estado | L39: Vista | M39: 12679480
A40: 11.666.268-k | B40: Activo | C40: F1 | D40: Zambrano Mandiola Bernarda Julia | E40: 45821 | G40: Indefinido | H40: Ordinaria ART 22 | I40: mensual | J40: Transferencia Bancaria | K40: Santander | L40: Corriente | M40: 79429856
A41: 26.432.526-9 | B41: Activo | C41: F1 | D41: Shephard Matos Francia Elizabeth | E41: 45815 | G41: Indefinido | H41: Ordinaria ART 22 | I41: mensual | J41: Transferencia Bancaria | K41: Banco Estado | L41: Vista | M41: 26432526
A42: 20.673.002-1 | B42: Activo | C42: F1 | D42: Roco Aguirre Enzo Valentino | E42: 45642 | G42: Indefinido | H42: Ordinaria ART 22 | I42: mensual | J42: Transferencia Bancaria | K42: BCI | L42: Corriente | M42: 777920673002
A43: 26.608.812-4 | B43: Activo | C43: F1 | D43: Pascal - Josie | E43: 45815 | G43: Indefinido | H43: Ordinaria ART 22 | I43: mensual | J43: Transferencia Bancaria | K43: Banco Estado | L43: Vista | M43: 26608812
A44: 12.876.804-1 | B44: Activo | C44: F1 | D44: Córdova Pismante María Silvana | E44: 45815 | G44: Indefinido | H44: Ordinaria ART 22 | I44: mensual | J44: Transferencia Bancaria | K44: BCI | L44: Vista | M44: 77176766
A45: 20.049.364-8 | B45: Activo | C45: F1 | D45: Cortés Romero Ignacio Javier | E45: 45873 | G45: Indefinido | H45: Ordinaria ART 22 | I45: mensual | J45: Transferencia Bancaria | K45: Banco Estado | L45: Vista | M45: 20049364
A46: 19.634.304-0 | B46: Activo | C46: F1 | D46: Saavedra Rivas Víctor Ariel | E46: 45873 | G46: Indefinido | H46: Ordinaria ART 22 | I46: mensual | J46: Transferencia Bancaria | K46: Banco Estado | L46: Vista | M46: 19634304
A47: 26.379.552-0 | B47: Inactivo | C47: F-1ago25 | D47: Martinez Jimenez Oswaldo Euclides | E47: 45873 | F47: 45946 | G47: Plazo fijo | H47: Ordinaria ART 22 | I47: mensual | J47: Transferencia Bancaria | K47: Banco Estado | L47: Vista | M47: 26379552 | N47: 45946 | O47: vencimiento_plazo | Q47: 45947
A48: 20.904.996-1 | B48: Inactivo | C48: F-4jul25 | D48: Arce Contreras Krishna Millaray | E48: 45868 | F48: 45936 | G48: Plazo fijo | H48: Ordinaria ART 22 | I48: mensual | J48: Transferencia Bancaria | K48: Scotiabank | L48: Corriente | M48: 988839361 | N48: 45936 | O48: vencimiento_plazo | Q48: 45940
A49: 28.689.407-0 | B49: Activo | C49: F-2jun25 | D49: Montaña Sequera Jose Gregorio | E49: 45820 | F49: 45973 | G49: Plazo fijo | H49: Ordinaria ART 22 | I49: mensual | J49: Cheque
A50: 21.014.986-4 | B50: Inactivo | C50: F-1ago25 | D50: Medina Santana Matías Andrés | E50: 45873 | F50: 45946 | G50: Plazo fijo | H50: Ordinaria ART 22 | I50: mensual | J50: Transferencia Bancaria | K50: Santander | L50: Corriente | M50: 79205907 | N50: 45946 | O50: vencimiento_plazo | Q50: 45947
A51: 17.317.967-7 | B51: Activo | C51: F1 | D51: Maldonado Castro Pablo Andrés | E51: 45873 | G51: Indefinido | H51: Ordinaria ART 22 | I51: mensual | J51: Transferencia Bancaria | K51: Santander | L51: Corriente | M51: 89632072
A52: 18.307.898-4 | B52: Inactivo | C52: F-1ago25 | D52: Barros Godoy Luis Paulo | E52: 45873 | F52: 45950 | G52: Plazo fijo | H52: Ordinaria ART 22 | I52: mensual | J52: Transferencia Bancaria | K52: Banco Estado | L52: Vista | M52: 18307898 | N52: 45950 | O52: vencimiento_plazo | Q52: 45954
A53: 17.105.874-0 | B53: Activo | C53: F1 | D53: Soñan Marifil Mariana Angelica | E53: 45810 | G53: Indefinido | H53: Ordinaria ART 22 | I53: mensual | J53: Transferencia Bancaria | K53: Banco Estado | L53: Vista | M53: 17105874
A54: 16.373.482-6 | B54: Activo | C54: F1 | D54: Fernández Gómez José Luis | E54: 45810 | G54: Indefinido | H54: Ordinaria ART 22 | I54: mensual | J54: Transferencia Bancaria | K54: Banco de Chile | L54: Vista | M54: 270324093
A55: 13.255.671-7 | B55: Activo | C55: F-1ago25 | D55: Gómez Zenteno Rafael Andrés | E55: 45873 | F55: 46026 | G55: Plazo fijo | H55: Ordinaria ART 22 | I55: mensual | J55: Transferencia Bancaria | K55: BCI | L55: Corriente | M55: 777913255671
A56: 14.131.634-6 | B56: Activo | C56: F1 | D56: Menchaca Fernández María Constanza | E56: 45803 | G56: Indefinido | H56: Exenta ART 22 | I56: mensual | J56: Transferencia Bancaria | K56: BICE | L56: Corriente | M56: 81724401
A57: 20.108.477-6 | B57: Activo | C57: F1 | D57: Moreno Laso Vicente Daniel | E57: 45810 | G57: Indefinido | H57: Ordinaria ART 22 | I57: mensual | J57: Transferencia Bancaria | K57: Falabella | L57: Corriente | M57: 19832281301
A58: 20.761.204-9 | B58: Activo | C58: F1 | D58: Parra Quezada Giulliana Stephani | E58: 45810 | G58: Indefinido | H58: Ordinaria ART 22 | I58: mensual | J58: Transferencia Bancaria | K58: Falabella | L58: Corriente | M58: 19802466515
A59: 10.807.412-4 | B59: Activo | C59: F1 | D59: Sáez Barrios Jean Eric | E59: 45810 | G59: Indefinido | H59: Exenta ART 22 | I59: mensual | J59: Transferencia Bancaria | K59: Santander | L59: Corriente | M59: 95000410
A60: 27.917.972-2 | B60: Activo | C60: F1 | D60: Fernandez Mambuscay Julian Estiben | E60: 44972 | G60: Indefinido | H60: Ordinaria ART 22 | I60: mensual | J60: Transferencia Bancaria | K60: Banco Estado | L60: Vista | M60: 27917972
A61: 26.409.239-6 | B61: Activo | C61: F1 | D61: Anzola Villalon Juan Carlos | E61: 43608 | G61: Indefinido | H61: Ordinaria ART 22 | I61: mensual | J61: Transferencia Bancaria | K61: Itau | L61: Vista | M61: 214468922
A62: 28.184.786-4 | B62: Activo | C62: F1 | D62: Feltran Loubens | E62: 45298 | G62: Indefinido | H62: Ordinaria ART 22 | I62: mensual | J62: Transferencia Bancaria | K62: BCI | L62: Vista | M62: 777928184786
A63: 21.355.332-1 | B63: Inactivo | C63: F-2sep25 | D63: Monroy Herrera Edelein Jeannette | E63: 45912 | F63: 45935 | G63: Plazo fijo | H63: Parcial ART 40 BIS | I63: diaria | J63: Transferencia Bancaria | K63: Banco Estado | L63: Vista | M63: 21355332 | N63: 45935 | O63: vencimiento_plazo | Q63: 45940
A64: 19.664.249-8 | B64: Inactivo | C64: F-1sep25 | D64: Martinez Beltran Victor Manuel | E64: 45904 | F64: 45931 | G64: Plazo fijo | H64: Ordinaria ART 22 | I64: mensual | J64: Transferencia Bancaria | K64: Banco Estado | L64: Vista | M64: 19664249 | N64: 45931 | O64: vencimiento_plazo | Q64: 45933
A65: 21.774.085-1 | B65: Inactivo | C65: F-1sep25 | D65: Jamed Cabezas Amanda Francisca | E65: 45904 | F65: 45931 | G65: Plazo fijo | H65: Ordinaria ART 22 | I65: mensual | J65: Transferencia Bancaria | K65: Banco Estado | L65: Vista | M65: 21774085 | N65: 45931 | O65: vencimiento_plazo | Q65: 45933
A66: 26.342.208-2 | B66: Activo | C66: F-1sep25 | D66: Meza Guzman Christian Modesto | E66: 45904 | F66: 45985 | G66: Plazo fijo | H66: Ordinaria ART 22 | I66: mensual | J66: Transferencia Bancaria | K66: Santander | L66: Corriente | M66: 80804407
A67: 19.824.335-3 | B67: Inactivo | C67: F-1sep25 | D67: Mardones Melo Esteban Elias | E67: 45903 | F67: 45949 | G67: Plazo fijo | H67: Ordinaria ART 22 | I67: mensual | J67: Transferencia Bancaria | K67: Banco Estado | L67: Vista | M67: 19824335 | N67: 45949 | O67: vencimiento_plazo | Q67: 45954
A68: 13.679.411-6 | B68: Activo | C68: F1 | D68: Irarrazabal Contreras Sabrina Gisella | E68: 45266 | G68: Indefinido | H68: Ordinaria ART 22 | I68: mensual | J68: Transferencia Bancaria | K68: Banco de Chile | L68: Corriente | M68: 505620363
A69: 17.217.358-6 | B69: Activo | C69: F1 | D69: Borquez Venegas Mario Alejandro | E69: 45278 | G69: Indefinido | H69: Ordinaria ART 22 | I69: mensual | J69: Transferencia Bancaria | K69: Banco Estado | L69: Vista | M69: 17217358
A70: 19.292.167-8 | B70: Activo | C70: F1 | D70: Martinez Pérez Francisca Andrea | E70: 45670 | G70: Indefinido | H70: Ordinaria ART 22 | I70: mensual | J70: Transferencia Bancaria | K70: Falabella | L70: Corriente | M70: 19997250641
A71: 19.736.484-k | B71: Activo | C71: F1 | D71: Arevalo Díaz Ignacio Alfonso | E71: 45666 | G71: Indefinido | H71: Ordinaria ART 22 | I71: mensual | J71: Transferencia Bancaria | K71: Banco de Chile | L71: Corriente | M71: 1952027008
A72: 18.097.808-9 | B72: Inactivo | C72: F-2ago25 | D72: Achurra Castro Christopher Abraham Segundo | E72: 45880 | F72: 45950 | G72: Plazo fijo | H72: Ordinaria ART 22 | I72: mensual | J72: Transferencia Bancaria | K72: Banco de Chile | L72: Corriente | M72: 8360022503 | N72: 45950 | O72: vencimiento_plazo | Q72: 45954
A73: 22.458.381-8 | B73: Inactivo | C73: F-2sep25 | D73: Ibañez Huaman Nalleli Brillid | E73: 45913 | F73: 45935 | G73: Plazo fijo | H73: Ordinaria ART 22 | I73: diaria | J73: Transferencia Bancaria | K73: Banco Estado | L73: Vista | M73: 22458381 | N73: 45935 | O73: vencimiento_plazo | Q73: 45940
A74: 10.730.616-1 | B74: Inactivo | C74: F-3ago25 | D74: Ortega Rideau Rolando Enrique | E74: 45887 | F74: 45948 | G74: Plazo fijo | H74: Ordinaria ART 22 | I74: mensual | J74: Transferencia Bancaria | K74: BCI | L74: Corriente | M74: 45413347 | N74: 45948 | O74: vencimiento_plazo | Q74: 45954
A75: 20.059.173-9 | B75: Activo | C75: F1 | D75: Medina Pino Amapola Belen | E75: 45683 | G75: Indefinido | H75: Ordinaria ART 22 | I75: mensual | J75: Transferencia Bancaria | K75: Santander | L75: Vista | M75: 5620059173
A76: 20.806.854-7 | B76: Inactivo | C76: F-2ago25 | D76: Antivilo Aguilar Sebastián Rodrigo | E76: 45880 | F76: 45945 | G76: Plazo fijo | H76: Ordinaria ART 22 | I76: mensual | J76: Transferencia Bancaria | K76: Santander | L76: Corriente | M76: 96576994 | N76: 45945 | O76: vencimiento_plazo | Q76: 45947
A77: 9.091.247-k | B77: Activo | C77: F-2ago25 | D77: Gonzalez Williams Ignacio Geronimo | E77: 45880 | F77: 45971 | G77: Plazo fijo | H77: Exenta ART 22 | I77: mensual | J77: Transferencia Bancaria | K77: Banco Estado | L77: Corriente | M77: 33600048185
A78: 20.164.622-7 | B78: Activo | C78: F1 | D78: Palma Chavez Juan Pablo | E78: 45666 | G78: Indefinido | H78: Ordinaria ART 22 | I78: mensual | J78: Transferencia Bancaria | K78: Banco Estado | L78: Vista | M78: 20164622
A79: 19.220.449-6 | B79: Inactivo | C79: F-3ago25 | D79: Garay Garay Samantha Gissella | E79: 45887 | F79: 45948 | G79: Plazo fijo | H79: Ordinaria ART 22 | I79: mensual | J79: Transferencia Bancaria | K79: Banco Estado | L79: Vista | M79: 19220449 | N79: 45948 | O79: vencimiento_plazo | Q79: 45954
A80: 19.986.412-2 | B80: Activo | C80: F1 | D80: Bustos Pradine Francisco Javier | E80: 45335 | G80: Indefinido | H80: Ordinaria ART 22 | I80: mensual | J80: Transferencia Bancaria | K80: Santander | L80: Corriente | M80: 79749907
A81: 21.408.179-2 | B81: Activo | C81: F1 | D81: Valdes Muñoz Maiva Ailyn | E81: 45203 | G81: Indefinido | H81: Ordinaria ART 22 | I81: mensual | J81: Transferencia Bancaria | K81: Falabella | L81: Corriente | M81: 15650064839
A82: 21.980.969-7 | B82: Inactivo | C82: F-2sep25 | D82: Contreras Gallardo Martin Ricardo | E82: 45913 | F82: 45948 | G82: Plazo fijo | H82: Ordinaria ART 22 | I82: mensual | J82: Transferencia Bancaria | K82: Banco Estado | L82: Vista | M82: 21980969 | N82: 45948 | O82: vencimiento_plazo | Q82: 45954
A83: 19.169.894-0 | B83: Inactivo | C83: F-3ago25 | D83: Toro Caniuñir Paula Francisca | E83: 45887 | F83: 45948 | G83: Plazo fijo | H83: Ordinaria ART 22 | I83: mensual | J83: Transferencia Bancaria | K83: Santander | L83: Corriente | M83: 85275585 | N83: 45948 | O83: vencimiento_plazo | Q83: 45954
A84: 21.790.892-2 | B84: Inactivo | C84: F-3ago25 | D84: Vera Porma Vania Alejandra | E84: 45887 | F84: 45948 | G84: Plazo fijo | H84: Ordinaria ART 22 | I84: mensual | J84: Transferencia Bancaria | K84: Banco Estado | L84: Vista | M84: 21790892 | N84: 45948 | O84: vencimiento_plazo | Q84: 45954
A85: 21.687.551-6 | B85: Activo | C85: F1 | D85: Riffo Carrera Alejandra Paz | E85: 45228 | G85: Indefinido | H85: Ordinaria ART 22 | I85: mensual | J85: Transferencia Bancaria | K85: Falabella | L85: Corriente | M85: 19841075631
A86: 21.747.982-7 | B86: Activo | C86: F1 | D86: Torres Arancibia Ignacio Antonio | E86: 45666 | G86: Indefinido | H86: Ordinaria ART 22 | I86: mensual | J86: Transferencia Bancaria | K86: Banco Estado | L86: Vista | M86: 21747982
A87: 18.522.905-k | B87: Activo | C87: F1 | D87: Cabezas Herrera Cristian Ignacio | E87: 45136 | G87: Indefinido | H87: Ordinaria ART 22 | I87: mensual | J87: Transferencia Bancaria | K87: Banco Estado | L87: Vista | M87: 18522905
A88: 12.264.591-6 | B88: Inactivo | C88: F-3ago25 | D88: Salinas Sanchez Paula Andrea | E88: 45887 | F88: 45946 | G88: Plazo fijo | H88: Ordinaria ART 22 | I88: mensual | J88: Transferencia Bancaria | K88: Banco de Chile | L88: Corriente | M88: 1591411510 | N88: 45946 | O88: vencimiento_plazo | Q88: 45947
A89: 11.395.482-5 | B89: Inactivo | C89: F-3ago25 | D89: Domínguez Saldaña Carla Verónica | E89: 45887 | F89: 45948 | G89: Plazo fijo | H89: Ordinaria ART 22 | I89: mensual | J89: Transferencia Bancaria | K89: Banco de Chile | L89: Vista | M89: 21019106 | N89: 45948 | O89: vencimiento_plazo | Q89: 45954
A90: 19.803.249-2 | B90: Activo | C90: F1 | D90: Caballero Francovich Nicole Carolina | E90: 45201 | G90: Indefinido | H90: Ordinaria ART 22 | I90: mensual | J90: Transferencia Bancaria | K90: Santander | L90: Corriente | M90: 73602904
A91: 18.938.881-0 | B91: Inactivo | C91: F-3ago25 | D91: Jorquera Saavedra Dara Abigail | E91: 45887 | F91: 45946 | G91: Plazo fijo | H91: Ordinaria ART 22 | I91: mensual | J91: Transferencia Bancaria | K91: Banco Estado | L91: Vista | M91: 82500329412 | N91: 45946 | O91: vencimiento_plazo | Q91: 45947
A92: 21.460.506-6 | B92: Inactivo | C92: F-3ago25 | D92: Valdés Eyzaguirre Jael Constanza | E92: 45887 | F92: 45946 | G92: Plazo fijo | H92: Ordinaria ART 22 | I92: mensual | J92: Transferencia Bancaria | K92: Banco de Chile | L92: Corriente | M92: 1760796503 | N92: 45946 | O92: vencimiento_plazo | Q92: 45947
A93: 10.647.429-k | B93: Activo | C93: F1 | D93: Medel Hernandez Bernarda Del Carmen | E93: 45139 | G93: Indefinido | H93: Ordinaria ART 22 | I93: mensual | J93: Transferencia Bancaria | K93: Banco Estado | L93: Vista | M93: 10647429
A94: 12.156.808-k | B94: Activo | C94: F1 | D94: Castillo Arroyo Maria Del Carmen | E94: 45615 | G94: Indefinido | H94: Ordinaria ART 22 | I94: mensual | J94: Transferencia Bancaria | K94: Banco Estado | L94: Vista | M94: 12156808
A95: 18.078.928-6 | B95: Activo | C95: F1 | D95: Santa Cruz Silva Constanza Deyanira | E95: 45375 | G95: Indefinido | H95: Ordinaria ART 22 | I95: mensual | J95: Transferencia Bancaria | K95: Santander | L95: Corriente | M95: 85375121
A96: 21.136.259-6 | B96: Activo | C96: F1 | D96: Segura Salva Marcela Monserratt | E96: 45623 | G96: Indefinido | H96: Ordinaria ART 22 | I96: mensual | J96: Transferencia Bancaria | K96: Banco Estado | L96: Vista | M96: 21136259
A97: 19.518.299-k | B97: Activo | C97: F1 | D97: Fuentes Alfaro Melissa Belen | E97: 45364 | G97: Indefinido | H97: Ordinaria ART 22 | I97: mensual | J97: Transferencia Bancaria | K97: Banco de Chile | L97: Vista | M97: 125723165
A98: 26.322.097-8 | B98: Activo | C98: F1 | D98: Georges Marie Laure | E98: 45580 | G98: Indefinido | H98: Ordinaria ART 22 | I98: mensual | J98: Transferencia Bancaria | K98: Banco Estado | L98: Vista | M98: 26322097
A99: 27.798.941-7 | B99: Activo | C99: F1 | D99: Garcia Sanchez Ilan Stev | E99: 45134 | G99: Indefinido | H99: Ordinaria ART 22 | I99: mensual | J99: Transferencia Bancaria | K99: Banco Estado | L99: Vista | M99: 27798941
A100: 18.221.904-5 | B100: Activo | C100: F1 | D100: Fuentes Valderrama Victor Roberto | E100: 45246 | G100: Indefinido | H100: Ordinaria ART 22 | I100: mensual | J100: Transferencia Bancaria | K100: Falabella | L100: Corriente | M100: 19822151240
A101: 19.958.979-2 | B101: Activo | C101: F1 | D101: Pizarro Vargas Joaquin Alonso | E101: 45434 | G101: Indefinido | H101: Ordinaria ART 22 | I101: mensual | J101: Transferencia Bancaria | K101: Banco de Chile | L101: Corriente | M101: 3102267509
...
